{
  "lastUpdated": "2026-05-08T14:11:28.408Z",
  "stocks": [
    {
      "symbol": "MU",
      "name": "Micron Technology, Inc.",
      "turnover": 9110000000,
      "price": 707.3,
      "changePercent": 9.38,
      "volume": 12880000,
      "marketCap": 797640000000,
      "peRatio": 33.39,
      "sector": "Electronic technology",
      "logo": "https://raw.githubusercontent.com/ZuluSpl0it/ticker-logos/main/ticker_icons/MU.png",
      "logoBackground": "#f8fafc"
    },
    {
      "symbol": "NVDA",
      "name": "NVIDIA Corporation",
      "turnover": 5960000000,
      "price": 217.14,
      "changePercent": 2.67,
      "volume": 27430000,
      "marketCap": 5280000000000,
      "peRatio": 44.3,
      "sector": "Electronic technology",
      "logo": "https://raw.githubusercontent.com/ZuluSpl0it/ticker-logos/main/ticker_icons/NVDA.png",
      "logoBackground": "#f8fafc"
    },
    {
      "symbol": "TSLA",
      "name": "Tesla, Inc.",
      "turnover": 5730000000,
      "price": 425.09,
      "changePercent": 3.23,
      "volume": 13480000,
      "marketCap": 1600000000000,
      "peRatio": 388.35,
      "sector": "Consumer durables",
      "logo": "https://raw.githubusercontent.com/ZuluSpl0it/ticker-logos/main/ticker_icons/TSLA.png",
      "logoBackground": "#f8fafc"
    },
    {
      "symbol": "SNDK",
      "name": "Sandisk Corporation",
      "turnover": 5610000000,
      "price": 1435.91,
      "changePercent": 7.16,
      "volume": 3910000,
      "marketCap": 212640000000,
      "peRatio": 49.92,
      "sector": "Electronic technology",
      "logo": "https://raw.githubusercontent.com/ZuluSpl0it/ticker-logos/main/ticker_icons/SNDK.png",
      "logoBackground": "#0f172a"
    },
    {
      "symbol": "AMD",
      "name": "Advanced Micro Devices, Inc.",
      "turnover": 4250000000,
      "price": 432.68,
      "changePercent": 5.93,
      "volume": 9820000,
      "marketCap": 705530000000,
      "peRatio": 142.01,
      "sector": "Electronic technology",
      "logo": "https://raw.githubusercontent.com/ZuluSpl0it/ticker-logos/main/ticker_icons/AMD.png",
      "logoBackground": "#f8fafc"
    },
    {
      "symbol": "INTC",
      "name": "Intel Corporation",
      "turnover": 2750000000,
      "price": 114.55,
      "changePercent": 4.5,
      "volume": 23990000,
      "marketCap": 575730000000,
      "peRatio": 0,
      "sector": "Electronic technology",
      "logo": "https://raw.githubusercontent.com/ZuluSpl0it/ticker-logos/main/ticker_icons/INTC.png",
      "logoBackground": "#0f172a"
    },
    {
      "symbol": "AAPL",
      "name": "Apple Inc.",
      "turnover": 2280000000,
      "price": 293.3,
      "changePercent": 2.04,
      "volume": 7790000,
      "marketCap": 4310000000000,
      "peRatio": 35.48,
      "sector": "Electronic technology",
      "logo": "https://raw.githubusercontent.com/ZuluSpl0it/ticker-logos/main/ticker_icons/AAPL.png",
      "logoBackground": "#0f172a"
    },
    {
      "symbol": "IREN",
      "name": "IREN Limited",
      "turnover": 2040000000,
      "price": 60.51,
      "changePercent": 6.43,
      "volume": 33690000,
      "marketCap": 20070000000,
      "peRatio": 209.94,
      "sector": "Technology services",
      "logo": "https://raw.githubusercontent.com/ZuluSpl0it/ticker-logos/main/ticker_icons/IREN.png",
      "logoBackground": ""
    },
    {
      "symbol": "MSFT",
      "name": "Microsoft Corporation",
      "turnover": 1780000000,
      "price": 416.66,
      "changePercent": -0.98,
      "volume": 4260000,
      "marketCap": 3100000000000,
      "peRatio": 24.82,
      "sector": "Technology services",
      "logo": "https://raw.githubusercontent.com/ZuluSpl0it/ticker-logos/main/ticker_icons/MSFT.png",
      "logoBackground": "#f8fafc"
    },
    {
      "symbol": "RKLB",
      "name": "Rocket Lab Corporation",
      "turnover": 1520000000,
      "price": 94.37,
      "changePercent": 20.09,
      "volume": 16140000,
      "marketCap": 54330000000,
      "peRatio": 0,
      "sector": "Electronic technology",
      "logo": "https://raw.githubusercontent.com/ZuluSpl0it/ticker-logos/main/ticker_icons/RKLB.png",
      "logoBackground": ""
    },
    {
      "symbol": "CRWV",
      "name": "CoreWeave, Inc.",
      "turnover": 1500000000,
      "price": 115.33,
      "changePercent": -10.49,
      "volume": 12980000,
      "marketCap": 63390000000,
      "peRatio": 0,
      "sector": "Technology services",
      "logo": "https://raw.githubusercontent.com/ZuluSpl0it/ticker-logos/main/ticker_icons/CRWV.png",
      "logoBackground": ""
    },
    {
      "symbol": "QCOM",
      "name": "QUALCOMM Incorporated",
      "turnover": 1460000000,
      "price": 216.22,
      "changePercent": 6.75,
      "volume": 6840000,
      "marketCap": 227900000000,
      "peRatio": 23.52,
      "sector": "Electronic technology",
      "logo": "https://raw.githubusercontent.com/ZuluSpl0it/ticker-logos/main/ticker_icons/QCOM.png",
      "logoBackground": ""
    },
    {
      "symbol": "AMZN",
      "name": "Amazon.com, Inc.",
      "turnover": 1290000000,
      "price": 273.15,
      "changePercent": 0.73,
      "volume": 4710000,
      "marketCap": 2940000000000,
      "peRatio": 32.64,
      "sector": "Retail trade",
      "logo": "https://raw.githubusercontent.com/ZuluSpl0it/ticker-logos/main/ticker_icons/AMZN.png",
      "logoBackground": "#0f172a"
    },
    {
      "symbol": "LITE",
      "name": "Lumentum Holdings Inc.",
      "turnover": 1150000000,
      "price": 927.47,
      "changePercent": 3.91,
      "volume": 1240000,
      "marketCap": 72160000000,
      "peRatio": 172.13,
      "sector": "Producer manufacturing",
      "logo": "https://raw.githubusercontent.com/ZuluSpl0it/ticker-logos/main/ticker_icons/LITE.png",
      "logoBackground": ""
    },
    {
      "symbol": "AVGO",
      "name": "Broadcom Inc.",
      "turnover": 1110000000,
      "price": 421.3,
      "changePercent": 2.12,
      "volume": 2640000,
      "marketCap": 1990000000000,
      "peRatio": 82.18,
      "sector": "Electronic technology",
      "logo": "https://raw.githubusercontent.com/ZuluSpl0it/ticker-logos/main/ticker_icons/AVGO.png",
      "logoBackground": "#f8fafc"
    },
    {
      "symbol": "PLTR",
      "name": "Palantir Technologies Inc.",
      "turnover": 1100000000,
      "price": 134.01,
      "changePercent": -2.21,
      "volume": 8200000,
      "marketCap": 321280000000,
      "peRatio": 150.99,
      "sector": "Technology services",
      "logo": "https://raw.githubusercontent.com/ZuluSpl0it/ticker-logos/main/ticker_icons/PLTR.png",
      "logoBackground": "#0f172a"
    },
    {
      "symbol": "GLW",
      "name": "Corning Incorporated",
      "turnover": 950930000,
      "price": 193.74,
      "changePercent": 6.21,
      "volume": 4940000,
      "marketCap": 166740000000,
      "peRatio": 92.99,
      "sector": "Electronic technology",
      "logo": "https://raw.githubusercontent.com/ZuluSpl0it/ticker-logos/main/ticker_icons/GLW.png",
      "logoBackground": "#0f172a"
    },
    {
      "symbol": "NET",
      "name": "Cloudflare, Inc.",
      "turnover": 882690000,
      "price": 202.77,
      "changePercent": -21.04,
      "volume": 4350000,
      "marketCap": 71370000000,
      "peRatio": 0,
      "sector": "Technology services",
      "logo": "https://raw.githubusercontent.com/ZuluSpl0it/ticker-logos/main/ticker_icons/NET.png",
      "logoBackground": ""
    },
    {
      "symbol": "AAOI",
      "name": "Applied Optoelectronics, Inc.",
      "turnover": 819060000,
      "price": 167.36,
      "changePercent": 6.23,
      "volume": 4890000,
      "marketCap": 13210000000,
      "peRatio": 0,
      "sector": "Electronic technology",
      "logo": "https://raw.githubusercontent.com/ZuluSpl0it/ticker-logos/main/ticker_icons/AAOI.png",
      "logoBackground": ""
    },
    {
      "symbol": "META",
      "name": "Meta Platforms, Inc.",
      "turnover": 816670000,
      "price": 614.05,
      "changePercent": -0.45,
      "volume": 1330000,
      "marketCap": 1560000000000,
      "peRatio": 22.32,
      "sector": "Technology services",
      "logo": "https://raw.githubusercontent.com/ZuluSpl0it/ticker-logos/main/ticker_icons/META.png",
      "logoBackground": "#f8fafc"
    },
    {
      "symbol": "ORCL",
      "name": "Oracle Corporation",
      "turnover": 788200000,
      "price": 191.63,
      "changePercent": -1.52,
      "volume": 4110000,
      "marketCap": 551130000000,
      "peRatio": 34.41,
      "sector": "Technology services",
      "logo": "https://raw.githubusercontent.com/ZuluSpl0it/ticker-logos/main/ticker_icons/ORCL.png",
      "logoBackground": "#f8fafc"
    },
    {
      "symbol": "AKAM",
      "name": "Akamai Technologies, Inc.",
      "turnover": 775350000,
      "price": 134.58,
      "changePercent": 15.33,
      "volume": 5760000,
      "marketCap": 19810000000,
      "peRatio": 45.31,
      "sector": "Technology services",
      "logo": "https://raw.githubusercontent.com/ZuluSpl0it/ticker-logos/main/ticker_icons/AKAM.png",
      "logoBackground": ""
    },
    {
      "symbol": "MELI",
      "name": "MercadoLibre, Inc.",
      "turnover": 685260000,
      "price": 1658.0,
      "changePercent": -11.34,
      "volume": 413300,
      "marketCap": 84060000000,
      "peRatio": 43.78,
      "sector": "Retail trade",
      "logo": "https://raw.githubusercontent.com/ZuluSpl0it/ticker-logos/main/ticker_icons/MELI.png",
      "logoBackground": ""
    },
    {
      "symbol": "GOOG",
      "name": "Alphabet Inc.",
      "turnover": 674980000,
      "price": 396.28,
      "changePercent": 0.25,
      "volume": 1700000,
      "marketCap": 4820000000000,
      "peRatio": 30.23,
      "sector": "Technology services",
      "logo": "https://raw.githubusercontent.com/ZuluSpl0it/ticker-logos/main/ticker_icons/GOOG.png",
      "logoBackground": "#f8fafc"
    },
    {
      "symbol": "INOD",
      "name": "Innodata Inc.",
      "turnover": 655220000,
      "price": 85.19,
      "changePercent": 86.66,
      "volume": 7690000,
      "marketCap": 2780000000,
      "peRatio": 93.32,
      "sector": "Technology services",
      "logo": "https://raw.githubusercontent.com/ZuluSpl0it/ticker-logos/main/ticker_icons/INOD.png",
      "logoBackground": ""
    },
    {
      "symbol": "COHR",
      "name": "Coherent Corp.",
      "turnover": 638550000,
      "price": 337.08,
      "changePercent": 5.61,
      "volume": 1890000,
      "marketCap": 65950000000,
      "peRatio": 160.93,
      "sector": "Electronic technology",
      "logo": "https://raw.githubusercontent.com/ZuluSpl0it/ticker-logos/main/ticker_icons/COHR.png",
      "logoBackground": ""
    },
    {
      "symbol": "WDC",
      "name": "Western Digital Corporation",
      "turnover": 576290000,
      "price": 482.49,
      "changePercent": 4.01,
      "volume": 1190000,
      "marketCap": 166310000000,
      "peRatio": 28.8,
      "sector": "Electronic technology",
      "logo": "https://raw.githubusercontent.com/ZuluSpl0it/ticker-logos/main/ticker_icons/WDC.png",
      "logoBackground": "#f8fafc"
    },
    {
      "symbol": "MRVL",
      "name": "Marvell Technology, Inc.",
      "turnover": 550010000,
      "price": 166.19,
      "changePercent": 3.86,
      "volume": 3310000,
      "marketCap": 145330000000,
      "peRatio": 53.77,
      "sector": "Electronic technology",
      "logo": "https://raw.githubusercontent.com/ZuluSpl0it/ticker-logos/main/ticker_icons/MRVL.png",
      "logoBackground": ""
    },
    {
      "symbol": "APP",
      "name": "Applovin Corporation",
      "turnover": 540840000,
      "price": 456.77,
      "changePercent": -8.44,
      "volume": 1180000,
      "marketCap": 153590000000,
      "peRatio": 40.29,
      "sector": "Technology services",
      "logo": "https://raw.githubusercontent.com/ZuluSpl0it/ticker-logos/main/ticker_icons/APP.png",
      "logoBackground": "#0f172a"
    },
    {
      "symbol": "BE",
      "name": "Bloom Energy Corporation",
      "turnover": 539760000,
      "price": 259.76,
      "changePercent": 0.43,
      "volume": 2080000,
      "marketCap": 73890000000,
      "peRatio": 0,
      "sector": "Electronic technology",
      "logo": "https://raw.githubusercontent.com/ZuluSpl0it/ticker-logos/main/ticker_icons/BE.png",
      "logoBackground": ""
    },
    {
      "symbol": "COIN",
      "name": "Coinbase Global, Inc.",
      "turnover": 501140000,
      "price": 183.34,
      "changePercent": -4.99,
      "volume": 2730000,
      "marketCap": 48420000000,
      "peRatio": 68.94,
      "sector": "Finance",
      "logo": "https://raw.githubusercontent.com/ZuluSpl0it/ticker-logos/main/ticker_icons/COIN.png",
      "logoBackground": "#f8fafc"
    },
    {
      "symbol": "STX",
      "name": "Seagate Technology Holdings PLC",
      "turnover": 478780000,
      "price": 789.5,
      "changePercent": 3.01,
      "volume": 606440,
      "marketCap": 177030000000,
      "peRatio": 74.94,
      "sector": "Electronic technology",
      "logo": "https://raw.githubusercontent.com/ZuluSpl0it/ticker-logos/main/ticker_icons/STX.png",
      "logoBackground": "#f8fafc"
    },
    {
      "symbol": "NOW",
      "name": "ServiceNow, Inc.",
      "turnover": 467970000,
      "price": 89.46,
      "changePercent": -4.42,
      "volume": 5230000,
      "marketCap": 92260000000,
      "peRatio": 53.21,
      "sector": "Technology services",
      "logo": "https://raw.githubusercontent.com/ZuluSpl0it/ticker-logos/main/ticker_icons/NOW.png",
      "logoBackground": "#0f172a"
    },
    {
      "symbol": "CRM",
      "name": "Salesforce, Inc.",
      "turnover": 458690000,
      "price": 177.72,
      "changePercent": -4.63,
      "volume": 2580000,
      "marketCap": 145380000000,
      "peRatio": 22.76,
      "sector": "Technology services",
      "logo": "https://raw.githubusercontent.com/ZuluSpl0it/ticker-logos/main/ticker_icons/CRM.png",
      "logoBackground": "#f8fafc"
    },
    {
      "symbol": "NBIS",
      "name": "Nebius Group N.V.",
      "turnover": 454720000,
      "price": 183.7,
      "changePercent": -0.58,
      "volume": 2480000,
      "marketCap": 46240000000,
      "peRatio": 360.41,
      "sector": "Technology services",
      "logo": "https://raw.githubusercontent.com/ZuluSpl0it/ticker-logos/main/ticker_icons/NBIS.png",
      "logoBackground": ""
    },
    {
      "symbol": "AXTI",
      "name": "AXT Inc",
      "turnover": 421340000,
      "price": 121.99,
      "changePercent": 12.52,
      "volume": 3450000,
      "marketCap": 6780000000,
      "peRatio": 0,
      "sector": "Electronic technology",
      "logo": "https://raw.githubusercontent.com/ZuluSpl0it/ticker-logos/main/ticker_icons/AXTI.png",
      "logoBackground": ""
    },
    {
      "symbol": "FLNC",
      "name": "Fluence Energy, Inc.",
      "turnover": 419620000,
      "price": 24.65,
      "changePercent": 29.94,
      "volume": 17020000,
      "marketCap": 4530000000,
      "peRatio": 0,
      "sector": "Producer manufacturing",
      "logo": "https://raw.githubusercontent.com/ZuluSpl0it/ticker-logos/main/ticker_icons/FLNC.png",
      "logoBackground": ""
    },
    {
      "symbol": "HUBS",
      "name": "HubSpot, Inc.",
      "turnover": 360670000,
      "price": 191.99,
      "changePercent": -21.23,
      "volume": 1880000,
      "marketCap": 9880000000,
      "peRatio": 220.68,
      "sector": "Technology services",
      "logo": "https://raw.githubusercontent.com/ZuluSpl0it/ticker-logos/main/ticker_icons/HUBS.png",
      "logoBackground": ""
    },
    {
      "symbol": "NFLX",
      "name": "Netflix, Inc.",
      "turnover": 321880000,
      "price": 87.43,
      "changePercent": -0.93,
      "volume": 3680000,
      "marketCap": 368150000000,
      "peRatio": 28.25,
      "sector": "Technology services",
      "logo": "https://raw.githubusercontent.com/ZuluSpl0it/ticker-logos/main/ticker_icons/NFLX.png",
      "logoBackground": "#f8fafc"
    },
    {
      "symbol": "DDOG",
      "name": "Datadog, Inc.",
      "turnover": 310720000,
      "price": 186.44,
      "changePercent": -1.21,
      "volume": 1670000,
      "marketCap": 65770000000,
      "peRatio": 500.51,
      "sector": "Technology services",
      "logo": "https://raw.githubusercontent.com/ZuluSpl0it/ticker-logos/main/ticker_icons/DDOG.png",
      "logoBackground": ""
    },
    {
      "symbol": "LLY",
      "name": "Eli Lilly and Company",
      "turnover": 293580000,
      "price": 958.6,
      "changePercent": -1.68,
      "volume": 306260,
      "marketCap": 902750000000,
      "peRatio": 34.51,
      "sector": "Health technology",
      "logo": "https://raw.githubusercontent.com/ZuluSpl0it/ticker-logos/main/ticker_icons/LLY.png",
      "logoBackground": "#f8fafc"
    },
    {
      "symbol": "CRCL",
      "name": "Circle Internet Group, Inc.",
      "turnover": 285480000,
      "price": 110.18,
      "changePercent": -2.71,
      "volume": 2590000,
      "marketCap": 27240000000,
      "peRatio": 0,
      "sector": "Technology services",
      "logo": "https://raw.githubusercontent.com/ZuluSpl0it/ticker-logos/main/ticker_icons/CRCL.png",
      "logoBackground": ""
    },
    {
      "symbol": "AMAT",
      "name": "Applied Materials, Inc.",
      "turnover": 281580000,
      "price": 430.04,
      "changePercent": 4.72,
      "volume": 654780,
      "marketCap": 341280000000,
      "peRatio": 44.05,
      "sector": "Producer manufacturing",
      "logo": "https://raw.githubusercontent.com/ZuluSpl0it/ticker-logos/main/ticker_icons/AMAT.png",
      "logoBackground": "#f8fafc"
    },
    {
      "symbol": "GEV",
      "name": "GE Vernova Inc.",
      "turnover": 275780000,
      "price": 1061.23,
      "changePercent": 1.49,
      "volume": 259870,
      "marketCap": 285170000000,
      "peRatio": 30.92,
      "sector": "Producer manufacturing",
      "logo": "https://raw.githubusercontent.com/ZuluSpl0it/ticker-logos/main/ticker_icons/GEV.png",
      "logoBackground": "darkdark"
    },
    {
      "symbol": "CAT",
      "name": "Caterpillar, Inc.",
      "turnover": 275560000,
      "price": 908.48,
      "changePercent": 1.43,
      "volume": 303320,
      "marketCap": 418480000000,
      "peRatio": 45.2,
      "sector": "Producer manufacturing",
      "logo": "https://raw.githubusercontent.com/ZuluSpl0it/ticker-logos/main/ticker_icons/CAT.png",
      "logoBackground": "#0f172a"
    },
    {
      "symbol": "HOOD",
      "name": "Robinhood Markets, Inc.",
      "turnover": 271190000,
      "price": 74.64,
      "changePercent": -2.15,
      "volume": 3630000,
      "marketCap": 67280000000,
      "peRatio": 36.1,
      "sector": "Finance",
      "logo": "https://raw.githubusercontent.com/ZuluSpl0it/ticker-logos/main/ticker_icons/HOOD.png",
      "logoBackground": "#f8fafc"
    },
    {
      "symbol": "ANET",
      "name": "Arista Networks, Inc.",
      "turnover": 267490000,
      "price": 142.57,
      "changePercent": 0.57,
      "volume": 1880000,
      "marketCap": 179520000000,
      "peRatio": 48.82,
      "sector": "Electronic technology",
      "logo": "https://raw.githubusercontent.com/ZuluSpl0it/ticker-logos/main/ticker_icons/ANET.png",
      "logoBackground": "#0f172a"
    },
    {
      "symbol": "UNH",
      "name": "UnitedHealth Group Incorporated",
      "turnover": 260280000,
      "price": 373.16,
      "changePercent": 0.92,
      "volume": 697510,
      "marketCap": 338880000000,
      "peRatio": 28.18,
      "sector": "Health services",
      "logo": "https://raw.githubusercontent.com/ZuluSpl0it/ticker-logos/main/ticker_icons/UNH.png",
      "logoBackground": "#0f172a"
    },
    {
      "symbol": "GILD",
      "name": "Gilead Sciences, Inc.",
      "turnover": 258950000,
      "price": 132.66,
      "changePercent": -1.05,
      "volume": 1950000,
      "marketCap": 164650000000,
      "peRatio": 18.05,
      "sector": "Health technology",
      "logo": "https://raw.githubusercontent.com/ZuluSpl0it/ticker-logos/main/ticker_icons/GILD.png",
      "logoBackground": ""
    },
    {
      "symbol": "CRWD",
      "name": "CrowdStrike Holdings, Inc.",
      "turnover": 256860000,
      "price": 498.12,
      "changePercent": -1.5,
      "volume": 515670,
      "marketCap": 126330000000,
      "peRatio": 0,
      "sector": "Technology services",
      "logo": "https://raw.githubusercontent.com/ZuluSpl0it/ticker-logos/main/ticker_icons/CRWD.png",
      "logoBackground": "#0f172a"
    },
    {
      "symbol": "C",
      "name": "Citigroup, Inc.",
      "turnover": 251420000,
      "price": 131.53,
      "changePercent": 1.89,
      "volume": 1910000,
      "marketCap": 225560000000,
      "peRatio": 16.3,
      "sector": "Finance",
      "logo": "https://raw.githubusercontent.com/ZuluSpl0it/ticker-logos/main/ticker_icons/C.png",
      "logoBackground": "#f8fafc"
    },
    {
      "symbol": "TTD",
      "name": "The Trade Desk, Inc.",
      "turnover": 247300000,
      "price": 21.45,
      "changePercent": -8.68,
      "volume": 11530000,
      "marketCap": 10210000000,
      "peRatio": 24.17,
      "sector": "Technology services",
      "logo": "https://raw.githubusercontent.com/ZuluSpl0it/ticker-logos/main/ticker_icons/TTD.png",
      "logoBackground": ""
    },
    {
      "symbol": "MSTR",
      "name": "Strategy Inc",
      "turnover": 246710000,
      "price": 178.39,
      "changePercent": -0.81,
      "volume": 1380000,
      "marketCap": 61760000000,
      "peRatio": 4.98,
      "sector": "Technology services",
      "logo": "https://raw.githubusercontent.com/ZuluSpl0it/ticker-logos/main/ticker_icons/MSTR.png",
      "logoBackground": ""
    },
    {
      "symbol": "MP",
      "name": "MP Materials Corp.",
      "turnover": 236920000,
      "price": 71.88,
      "changePercent": 3.98,
      "volume": 3300000,
      "marketCap": 12770000000,
      "peRatio": 0,
      "sector": "Non-energy minerals",
      "logo": "https://raw.githubusercontent.com/ZuluSpl0it/ticker-logos/main/ticker_icons/MP.png",
      "logoBackground": ""
    },
    {
      "symbol": "JPM",
      "name": "JP Morgan Chase & Co.",
      "turnover": 228060000,
      "price": 307.9,
      "changePercent": 0.53,
      "volume": 740690,
      "marketCap": 825020000000,
      "peRatio": 14.75,
      "sector": "Finance",
      "logo": "https://raw.githubusercontent.com/ZuluSpl0it/ticker-logos/main/ticker_icons/JPM.png",
      "logoBackground": "#f8fafc"
    },
    {
      "symbol": "KLAC",
      "name": "KLA Corporation",
      "turnover": 226360000,
      "price": 1859.75,
      "changePercent": 5.47,
      "volume": 121710,
      "marketCap": 242930000000,
      "peRatio": 52.58,
      "sector": "Electronic technology",
      "logo": "https://raw.githubusercontent.com/ZuluSpl0it/ticker-logos/main/ticker_icons/KLAC.png",
      "logoBackground": ""
    },
    {
      "symbol": "SMCI",
      "name": "Super Micro Computer, Inc.",
      "turnover": 226070000,
      "price": 33.23,
      "changePercent": -1.16,
      "volume": 6800000,
      "marketCap": 19900000000,
      "peRatio": 17.57,
      "sector": "Electronic technology",
      "logo": "https://raw.githubusercontent.com/ZuluSpl0it/ticker-logos/main/ticker_icons/SMCI.png",
      "logoBackground": ""
    },
    {
      "symbol": "LRCX",
      "name": "Lam Research Corporation",
      "turnover": 223300000,
      "price": 293.49,
      "changePercent": 2.43,
      "volume": 760850,
      "marketCap": 367030000000,
      "peRatio": 55.4,
      "sector": "Producer manufacturing",
      "logo": "https://raw.githubusercontent.com/ZuluSpl0it/ticker-logos/main/ticker_icons/LRCX.png",
      "logoBackground": "#0f172a"
    },
    {
      "symbol": "TMO",
      "name": "Thermo Fisher Scientific Inc",
      "turnover": 217630000,
      "price": 460.89,
      "changePercent": -2.88,
      "volume": 472200,
      "marketCap": 171270000000,
      "peRatio": 25.34,
      "sector": "Health technology",
      "logo": "https://raw.githubusercontent.com/ZuluSpl0it/ticker-logos/main/ticker_icons/TMO.png",
      "logoBackground": ""
    },
    {
      "symbol": "TXN",
      "name": "Texas Instruments Incorporated",
      "turnover": 217540000,
      "price": 289.94,
      "changePercent": 1.65,
      "volume": 750300,
      "marketCap": 263870000000,
      "peRatio": 49.6,
      "sector": "Electronic technology",
      "logo": "https://raw.githubusercontent.com/ZuluSpl0it/ticker-logos/main/ticker_icons/TXN.png",
      "logoBackground": "#f8fafc"
    },
    {
      "symbol": "EXPE",
      "name": "Expedia Group, Inc.",
      "turnover": 216310000,
      "price": 230.58,
      "changePercent": -8.79,
      "volume": 938100,
      "marketCap": 28250000000,
      "peRatio": 20.31,
      "sector": "Consumer services",
      "logo": "https://raw.githubusercontent.com/ZuluSpl0it/ticker-logos/main/ticker_icons/EXPE.png",
      "logoBackground": ""
    },
    {
      "symbol": "UBER",
      "name": "Uber Technologies, Inc.",
      "turnover": 215740000,
      "price": 74.59,
      "changePercent": -2.78,
      "volume": 2890000,
      "marketCap": 151840000000,
      "peRatio": 18.59,
      "sector": "Transportation",
      "logo": "https://raw.githubusercontent.com/ZuluSpl0it/ticker-logos/main/ticker_icons/UBER.png",
      "logoBackground": ""
    },
    {
      "symbol": "V",
      "name": "Visa Inc.",
      "turnover": 213330000,
      "price": 316.84,
      "changePercent": -1.4,
      "volume": 673290,
      "marketCap": 596970000000,
      "peRatio": 27.85,
      "sector": "Finance",
      "logo": "https://raw.githubusercontent.com/ZuluSpl0it/ticker-logos/main/ticker_icons/V.png",
      "logoBackground": "#0f172a"
    },
    {
      "symbol": "DKNG",
      "name": "DraftKings Inc.",
      "turnover": 212860000,
      "price": 25.89,
      "changePercent": 2.66,
      "volume": 8220000,
      "marketCap": 12830000000,
      "peRatio": 435.86,
      "sector": "Consumer services",
      "logo": "https://raw.githubusercontent.com/ZuluSpl0it/ticker-logos/main/ticker_icons/DKNG.png",
      "logoBackground": ""
    },
    {
      "symbol": "ASTS",
      "name": "AST SpaceMobile, Inc.",
      "turnover": 211120000,
      "price": 68.5,
      "changePercent": 4.81,
      "volume": 3080000,
      "marketCap": 26580000000,
      "peRatio": 0,
      "sector": "Communications",
      "logo": "https://raw.githubusercontent.com/ZuluSpl0it/ticker-logos/main/ticker_icons/ASTS.png",
      "logoBackground": ""
    },
    {
      "symbol": "ADBE",
      "name": "Adobe Inc.",
      "turnover": 210800000,
      "price": 246.84,
      "changePercent": -3.77,
      "volume": 853990,
      "marketCap": 99770000000,
      "peRatio": 14.38,
      "sector": "Technology services",
      "logo": "https://raw.githubusercontent.com/ZuluSpl0it/ticker-logos/main/ticker_icons/ADBE.png",
      "logoBackground": "#f8fafc"
    },
    {
      "symbol": "CSCO",
      "name": "Cisco Systems, Inc.",
      "turnover": 208260000,
      "price": 94.39,
      "changePercent": 2.42,
      "volume": 2210000,
      "marketCap": 372830000000,
      "peRatio": 33.2,
      "sector": "Electronic technology",
      "logo": "https://raw.githubusercontent.com/ZuluSpl0it/ticker-logos/main/ticker_icons/CSCO.png",
      "logoBackground": "#f8fafc"
    },
    {
      "symbol": "IONQ",
      "name": "IonQ, Inc.",
      "turnover": 205540000,
      "price": 47.59,
      "changePercent": -0.19,
      "volume": 4320000,
      "marketCap": 17450000000,
      "peRatio": 0,
      "sector": "Electronic technology",
      "logo": "https://raw.githubusercontent.com/ZuluSpl0it/ticker-logos/main/ticker_icons/IONQ.png",
      "logoBackground": ""
    },
    {
      "symbol": "WULF",
      "name": "TeraWulf Inc.",
      "turnover": 204790000,
      "price": 23.3,
      "changePercent": -3.0,
      "volume": 8790000,
      "marketCap": 11250000000,
      "peRatio": 0,
      "sector": "Technology services",
      "logo": "https://raw.githubusercontent.com/ZuluSpl0it/ticker-logos/main/ticker_icons/WULF.png",
      "logoBackground": ""
    },
    {
      "symbol": "MA",
      "name": "Mastercard Incorporated",
      "turnover": 202070000,
      "price": 492.5,
      "changePercent": -1.68,
      "volume": 410290,
      "marketCap": 435390000000,
      "peRatio": 28.5,
      "sector": "Finance",
      "logo": "https://raw.githubusercontent.com/ZuluSpl0it/ticker-logos/main/ticker_icons/MA.png",
      "logoBackground": "#f8fafc"
    },
    {
      "symbol": "PANW",
      "name": "Palo Alto Networks, Inc.",
      "turnover": 190650000,
      "price": 193.95,
      "changePercent": -1.31,
      "volume": 982980,
      "marketCap": 158260000000,
      "peRatio": 107.32,
      "sector": "Technology services",
      "logo": "https://raw.githubusercontent.com/ZuluSpl0it/ticker-logos/main/ticker_icons/PANW.png",
      "logoBackground": "#f8fafc"
    },
    {
      "symbol": "XYZ",
      "name": "Block, Inc.",
      "turnover": 190380000,
      "price": 72.72,
      "changePercent": 3.68,
      "volume": 2620000,
      "marketCap": 43320000000,
      "peRatio": 34.55,
      "sector": "Commercial services",
      "logo": "https://raw.githubusercontent.com/ZuluSpl0it/ticker-logos/main/ticker_icons/XYZ.png",
      "logoBackground": ""
    },
    {
      "symbol": "XOM",
      "name": "Exxon Mobil Corporation",
      "turnover": 189880000,
      "price": 144.7,
      "changePercent": -1.28,
      "volume": 1310000,
      "marketCap": 599770000000,
      "peRatio": 24.42,
      "sector": "Energy minerals",
      "logo": "https://raw.githubusercontent.com/ZuluSpl0it/ticker-logos/main/ticker_icons/XOM.png",
      "logoBackground": "#f8fafc"
    },
    {
      "symbol": "MCK",
      "name": "McKesson Corporation",
      "turnover": 189010000,
      "price": 754.2,
      "changePercent": -0.07,
      "volume": 250610,
      "marketCap": 92380000000,
      "peRatio": 21.69,
      "sector": "Distribution services",
      "logo": "https://raw.githubusercontent.com/ZuluSpl0it/ticker-logos/main/ticker_icons/MCK.png",
      "logoBackground": ""
    },
    {
      "symbol": "VRT",
      "name": "Vertiv Holdings, LLC",
      "turnover": 184430000,
      "price": 347.7,
      "changePercent": 2.26,
      "volume": 530440,
      "marketCap": 133550000000,
      "peRatio": 87.28,
      "sector": "Electronic technology",
      "logo": "https://raw.githubusercontent.com/ZuluSpl0it/ticker-logos/main/ticker_icons/VRT.png",
      "logoBackground": ""
    },
    {
      "symbol": "WMT",
      "name": "Walmart Inc.",
      "turnover": 172620000,
      "price": 130.82,
      "changePercent": 0.48,
      "volume": 1320000,
      "marketCap": 1040000000000,
      "peRatio": 47.92,
      "sector": "Retail trade",
      "logo": "https://raw.githubusercontent.com/ZuluSpl0it/ticker-logos/main/ticker_icons/WMT.png",
      "logoBackground": "#0f172a"
    },
    {
      "symbol": "MCHP",
      "name": "Microchip Technology Incorporated",
      "turnover": 171230000,
      "price": 101.08,
      "changePercent": -0.49,
      "volume": 1690000,
      "marketCap": 54700000000,
      "peRatio": 0,
      "sector": "Electronic technology",
      "logo": "https://raw.githubusercontent.com/ZuluSpl0it/ticker-logos/main/ticker_icons/MCHP.png",
      "logoBackground": ""
    },
    {
      "symbol": "ABNB",
      "name": "Airbnb, Inc.",
      "turnover": 167920000,
      "price": 141.41,
      "changePercent": 0.68,
      "volume": 1190000,
      "marketCap": 85420000000,
      "peRatio": 34.83,
      "sector": "Consumer services",
      "logo": "https://raw.githubusercontent.com/ZuluSpl0it/ticker-logos/main/ticker_icons/ABNB.png",
      "logoBackground": ""
    },
    {
      "symbol": "POET",
      "name": "POET Technologies Inc.",
      "turnover": 162750000,
      "price": 10.59,
      "changePercent": 10.51,
      "volume": 15370000,
      "marketCap": 1620000000,
      "peRatio": 0,
      "sector": "Producer manufacturing No rating",
      "logo": "https://raw.githubusercontent.com/ZuluSpl0it/ticker-logos/main/ticker_icons/POET.png",
      "logoBackground": ""
    },
    {
      "symbol": "BA",
      "name": "Boeing Company (The)",
      "turnover": 161290000,
      "price": 232.73,
      "changePercent": 0.73,
      "volume": 693030,
      "marketCap": 183460000000,
      "peRatio": 119.65,
      "sector": "Electronic technology",
      "logo": "https://raw.githubusercontent.com/ZuluSpl0it/ticker-logos/main/ticker_icons/BA.png",
      "logoBackground": "#0f172a"
    },
    {
      "symbol": "WFC",
      "name": "Wells Fargo & Company",
      "turnover": 157360000,
      "price": 78.18,
      "changePercent": -1.24,
      "volume": 2010000,
      "marketCap": 239250000000,
      "peRatio": 12.07,
      "sector": "Finance",
      "logo": "https://raw.githubusercontent.com/ZuluSpl0it/ticker-logos/main/ticker_icons/WFC.png",
      "logoBackground": "#f8fafc"
    },
    {
      "symbol": "OKLO",
      "name": "Oklo Inc.",
      "turnover": 157270000,
      "price": 71.33,
      "changePercent": -0.7,
      "volume": 2200000,
      "marketCap": 12380000000,
      "peRatio": 0,
      "sector": "Producer manufacturing",
      "logo": "https://raw.githubusercontent.com/ZuluSpl0it/ticker-logos/main/ticker_icons/OKLO.png",
      "logoBackground": ""
    },
    {
      "symbol": "APH",
      "name": "Amphenol Corporation",
      "turnover": 157190000,
      "price": 134.45,
      "changePercent": -1.59,
      "volume": 1170000,
      "marketCap": 165410000000,
      "peRatio": 38.64,
      "sector": "Electronic technology",
      "logo": "https://raw.githubusercontent.com/ZuluSpl0it/ticker-logos/main/ticker_icons/APH.png",
      "logoBackground": "#0f172a"
    },
    {
      "symbol": "IBM",
      "name": "International Business Machines Corporation",
      "turnover": 156110000,
      "price": 225.73,
      "changePercent": -2.41,
      "volume": 691580,
      "marketCap": 212160000000,
      "peRatio": 19.96,
      "sector": "Technology services",
      "logo": "https://raw.githubusercontent.com/ZuluSpl0it/ticker-logos/main/ticker_icons/IBM.png",
      "logoBackground": ""
    },
    {
      "symbol": "TOST",
      "name": "Toast, Inc.",
      "turnover": 155890000,
      "price": 24.39,
      "changePercent": -16.98,
      "volume": 6390000,
      "marketCap": 14370000000,
      "peRatio": 37.07,
      "sector": "Technology services",
      "logo": "https://raw.githubusercontent.com/ZuluSpl0it/ticker-logos/main/ticker_icons/TOST.png",
      "logoBackground": ""
    },
    {
      "symbol": "PFE",
      "name": "Pfizer, Inc.",
      "turnover": 151820000,
      "price": 25.89,
      "changePercent": -2.23,
      "volume": 5860000,
      "marketCap": 147560000000,
      "peRatio": 19.85,
      "sector": "Health technology",
      "logo": "https://raw.githubusercontent.com/ZuluSpl0it/ticker-logos/main/ticker_icons/PFE.png",
      "logoBackground": ""
    },
    {
      "symbol": "GS",
      "name": "Goldman Sachs Group, Inc. (The)",
      "turnover": 151810000,
      "price": 938.09,
      "changePercent": 1.32,
      "volume": 161820,
      "marketCap": 276740000000,
      "peRatio": 17.14,
      "sector": "Finance",
      "logo": "https://raw.githubusercontent.com/ZuluSpl0it/ticker-logos/main/ticker_icons/GS.png",
      "logoBackground": "#f8fafc"
    },
    {
      "symbol": "BAC",
      "name": "Bank of America Corporation",
      "turnover": 151480000,
      "price": 52.46,
      "changePercent": -0.55,
      "volume": 2890000,
      "marketCap": 372290000000,
      "peRatio": 13.02,
      "sector": "Finance",
      "logo": "https://raw.githubusercontent.com/ZuluSpl0it/ticker-logos/main/ticker_icons/BAC.png",
      "logoBackground": "#f8fafc"
    },
    {
      "symbol": "TER",
      "name": "Teradyne, Inc.",
      "turnover": 151080000,
      "price": 362.85,
      "changePercent": 2.47,
      "volume": 416370,
      "marketCap": 56800000000,
      "peRatio": 67.16,
      "sector": "Electronic technology",
      "logo": "https://raw.githubusercontent.com/ZuluSpl0it/ticker-logos/main/ticker_icons/TER.png",
      "logoBackground": ""
    },
    {
      "symbol": "GE",
      "name": "GE Aerospace",
      "turnover": 150230000,
      "price": 304.57,
      "changePercent": 0.64,
      "volume": 493250,
      "marketCap": 317760000000,
      "peRatio": 37.54,
      "sector": "Electronic technology",
      "logo": "https://raw.githubusercontent.com/ZuluSpl0it/ticker-logos/main/ticker_icons/GE.png",
      "logoBackground": "#f8fafc"
    },
    {
      "symbol": "MCD",
      "name": "McDonald's Corporation",
      "turnover": 150150000,
      "price": 280.75,
      "changePercent": -1.04,
      "volume": 534800,
      "marketCap": 199560000000,
      "peRatio": 23.14,
      "sector": "Consumer services",
      "logo": "https://raw.githubusercontent.com/ZuluSpl0it/ticker-logos/main/ticker_icons/MCD.png",
      "logoBackground": ""
    },
    {
      "symbol": "INTU",
      "name": "Intuit Inc.",
      "turnover": 149650000,
      "price": 388.03,
      "changePercent": -4.61,
      "volume": 385670,
      "marketCap": 107310000000,
      "peRatio": 25.17,
      "sector": "Technology services",
      "logo": "https://raw.githubusercontent.com/ZuluSpl0it/ticker-logos/main/ticker_icons/INTU.png",
      "logoBackground": ""
    },
    {
      "symbol": "DASH",
      "name": "DoorDash, Inc.",
      "turnover": 147510000,
      "price": 163.57,
      "changePercent": -4.54,
      "volume": 901790,
      "marketCap": 71060000000,
      "peRatio": 77.91,
      "sector": "Transportation",
      "logo": "https://raw.githubusercontent.com/ZuluSpl0it/ticker-logos/main/ticker_icons/DASH.png",
      "logoBackground": ""
    },
    {
      "symbol": "SOFI",
      "name": "SoFi Technologies, Inc.",
      "turnover": 146090000,
      "price": 15.78,
      "changePercent": -1.41,
      "volume": 9260000,
      "marketCap": 20120000000,
      "peRatio": 35.78,
      "sector": "Finance",
      "logo": "https://raw.githubusercontent.com/ZuluSpl0it/ticker-logos/main/ticker_icons/SOFI.png",
      "logoBackground": ""
    },
    {
      "symbol": "ZTS",
      "name": "Zoetis Inc.",
      "turnover": 145610000,
      "price": 84.38,
      "changePercent": -3.36,
      "volume": 1730000,
      "marketCap": 35480000000,
      "peRatio": 13.98,
      "sector": "Health technology",
      "logo": "https://raw.githubusercontent.com/ZuluSpl0it/ticker-logos/main/ticker_icons/ZTS.png",
      "logoBackground": ""
    },
    {
      "symbol": "SNOW",
      "name": "Snowflake Inc.",
      "turnover": 143620000,
      "price": 145.35,
      "changePercent": -5.44,
      "volume": 988090,
      "marketCap": 50250000000,
      "peRatio": 0,
      "sector": "Technology services",
      "logo": "https://raw.githubusercontent.com/ZuluSpl0it/ticker-logos/main/ticker_icons/SNOW.png",
      "logoBackground": ""
    },
    {
      "symbol": "SHOP",
      "name": "Shopify Inc.",
      "turnover": 143400000,
      "price": 109.07,
      "changePercent": -2.39,
      "volume": 1310000,
      "marketCap": 142230000000,
      "peRatio": 106.96,
      "sector": "Commercial services",
      "logo": "https://raw.githubusercontent.com/ZuluSpl0it/ticker-logos/main/ticker_icons/SHOP.png",
      "logoBackground": ""
    },
    {
      "symbol": "VST",
      "name": "Vistra Corp.",
      "turnover": 140890000,
      "price": 150.38,
      "changePercent": -2.32,
      "volume": 936890,
      "marketCap": 50910000000,
      "peRatio": 24.99,
      "sector": "Utilities",
      "logo": "https://raw.githubusercontent.com/ZuluSpl0it/ticker-logos/main/ticker_icons/VST.png",
      "logoBackground": ""
    },
    {
      "symbol": "DELL",
      "name": "Dell Technologies Inc.",
      "turnover": 138940000,
      "price": 240.25,
      "changePercent": 4.33,
      "volume": 578330,
      "marketCap": 156890000000,
      "peRatio": 27.56,
      "sector": "Electronic technology",
      "logo": "https://raw.githubusercontent.com/ZuluSpl0it/ticker-logos/main/ticker_icons/DELL.png",
      "logoBackground": ""
    },
    {
      "symbol": "RXT",
      "name": "Rackspace Technology, Inc.",
      "turnover": 137300000,
      "price": 4.23,
      "changePercent": 20.21,
      "volume": 32330000,
      "marketCap": 1040000000,
      "peRatio": 0,
      "sector": "Technology services",
      "logo": "https://raw.githubusercontent.com/ZuluSpl0it/ticker-logos/main/ticker_icons/RXT.png",
      "logoBackground": ""
    }
  ],
  "indices": [
    {
      "symbol": "^GSPC",
      "name": "S&P 500",
      "value": 4950.25,
      "change": 22.14,
      "changePercent": 0.45
    },
    {
      "symbol": "^DJI",
      "name": "Dow Jones",
      "value": 38850.12,
      "change": -48.22,
      "changePercent": -0.12
    },
    {
      "symbol": "^IXIC",
      "name": "Nasdaq",
      "value": 15720.88,
      "change": 68.33,
      "changePercent": 0.44
    },
    {
      "symbol": "^RUT",
      "name": "Russell 2000",
      "value": 1986.1,
      "change": 7.05,
      "changePercent": 0.36
    }
  ],
  "sectors": [
    {
      "name": "Electronic technology",
      "change": 3.99,
      "topStock": "RKLB"
    },
    {
      "name": "Consumer durables",
      "change": 3.23,
      "topStock": "TSLA"
    },
    {
      "name": "Technology services",
      "change": -0.02,
      "topStock": "INOD"
    },
    {
      "name": "Retail trade",
      "change": -3.38,
      "topStock": "AMZN"
    },
    {
      "name": "Producer manufacturing",
      "change": 6.17,
      "topStock": "FLNC"
    },
    {
      "name": "Finance",
      "change": -0.97,
      "topStock": "C"
    },
    {
      "name": "Health technology",
      "change": -2.24,
      "topStock": "GILD"
    },
    {
      "name": "Health services",
      "change": 0.92,
      "topStock": "UNH"
    },
    {
      "name": "Non-energy minerals",
      "change": 3.98,
      "topStock": "MP"
    },
    {
      "name": "Consumer services",
      "change": -1.62,
      "topStock": "DKNG"
    },
    {
      "name": "Transportation",
      "change": -3.66,
      "topStock": "UBER"
    },
    {
      "name": "Communications",
      "change": 4.81,
      "topStock": "ASTS"
    },
    {
      "name": "Commercial services",
      "change": 0.65,
      "topStock": "XYZ"
    },
    {
      "name": "Energy minerals",
      "change": -1.28,
      "topStock": "XOM"
    },
    {
      "name": "Distribution services",
      "change": -0.07,
      "topStock": "MCK"
    },
    {
      "name": "Producer manufacturing No rating",
      "change": 10.51,
      "topStock": "POET"
    },
    {
      "name": "Utilities",
      "change": -2.32,
      "topStock": "VST"
    }
  ]
}
