{
  "lastProcessedHeight": 28651789,
  "pairs": {
    "cwlunc-lunc": {
      "baseOrStartSymbol": "CWLUNC",
      "currentHourId": 494177,
      "hourVolumeUsdEstimate": 1.187405489835,
      "pairId": "cwlunc-lunc",
      "pairType": "legacy",
      "quoteOrEndSymbol": "LUNC",
      "raw": {
        "hourVolumePrimary": 14762.151802,
        "hourVolumeSecondary": 14688.341042,
        "volume24hPrimary": 762326.818342,
        "volume24hSecondary": 762120.938972,
        "volume7dPrimary": 18039816.630018998,
        "volume7dSecondary": 18022944.03864
      },
      "swapCount24h": 6,
      "swapCount7d": 149,
      "volume24hUsdEstimate": 61.609856706496,
      "volume7dUsdEstimate": 1456.974796083658
    },
    "rebase-cwustc": {
      "baseOrStartSymbol": "REBASE",
      "currentHourId": 494177,
      "hourVolumeUsdEstimate": 0.0,
      "pairId": "rebase-cwustc",
      "pairType": "legacy",
      "quoteOrEndSymbol": "CWUSTC",
      "raw": {
        "hourVolumePrimary": 0.0,
        "hourVolumeSecondary": 0.0,
        "volume24hPrimary": 0.0,
        "volume24hSecondary": 0.0,
        "volume7dPrimary": 40.011347,
        "volume7dSecondary": 21.910491
      },
      "swapCount24h": 0,
      "swapCount7d": 1,
      "volume24hUsdEstimate": 0.0,
      "volume7dUsdEstimate": 0.141496855353
    },
    "rebase-ustc": {
      "baseOrStartSymbol": "REBASE",
      "currentHourId": 494177,
      "hourVolumeUsdEstimate": 3.348477776094,
      "pairId": "rebase-ustc",
      "pairType": "legacy",
      "quoteOrEndSymbol": "USTC",
      "raw": {
        "hourVolumePrimary": 941.130776,
        "hourVolumeSecondary": 518.504754,
        "volume24hPrimary": 40667.674068,
        "volume24hSecondary": 22223.355373,
        "volume7dPrimary": 247239.98022,
        "volume7dSecondary": 134937.24217
      },
      "swapCount24h": 101,
      "swapCount7d": 575,
      "volume24hUsdEstimate": 143.517317831065,
      "volume7dUsdEstimate": 871.417963071752
    },
    "weso-cwlunc": {
      "baseOrStartSymbol": "WESO",
      "currentHourId": 494177,
      "hourVolumeUsdEstimate": 0.0,
      "pairId": "weso-cwlunc",
      "pairType": "legacy",
      "quoteOrEndSymbol": "CWLUNC",
      "raw": {
        "hourVolumePrimary": 0.0,
        "hourVolumeSecondary": 0.0,
        "volume24hPrimary": 0.0,
        "volume24hSecondary": 0.0,
        "volume7dPrimary": 3659.026065,
        "volume7dSecondary": 147071.806158
      },
      "swapCount24h": 0,
      "swapCount7d": 2,
      "volume24hUsdEstimate": 0.0,
      "volume7dUsdEstimate": 11.889284809813
    },
    "weso-lunc": {
      "baseOrStartSymbol": "WESO",
      "currentHourId": 494177,
      "hourVolumeUsdEstimate": 13.269262980671,
      "pairId": "weso-lunc",
      "pairType": "legacy",
      "quoteOrEndSymbol": "LUNC",
      "raw": {
        "hourVolumePrimary": 4071.76887,
        "hourVolumeSecondary": 164142.29318,
        "volume24hPrimary": 88672.32982300001,
        "volume24hSecondary": 3566759.07889,
        "volume7dPrimary": 845318.889294,
        "volume7dSecondary": 34065089.568142004
      },
      "swapCount24h": 169,
      "swapCount7d": 1141,
      "volume24hUsdEstimate": 288.336803937468,
      "volume7dUsdEstimate": 2753.8218406886
    }
  },
  "prices": {
    "LUNC": 8.084e-05,
    "USTC": 0.00645795
  },
  "updatedAtIso": "2026-05-17T17:54:14.742341+00:00"
}