{
  "lastProcessedHeight": 28857296,
  "pairs": {
    "cwlunc-lunc": {
      "baseOrStartSymbol": "CWLUNC",
      "currentHourId": 494514,
      "hourVolumeUsdEstimate": 0.0,
      "pairId": "cwlunc-lunc",
      "pairType": "legacy",
      "quoteOrEndSymbol": "LUNC",
      "raw": {
        "hourVolumePrimary": 0.0,
        "hourVolumeSecondary": 0.0,
        "volume24hPrimary": 30485101.832617998,
        "volume24hSecondary": 30361044.578973,
        "volume7dPrimary": 114139182.421872,
        "volume7dSecondary": 113961674.862514
      },
      "swapCount24h": 109,
      "swapCount7d": 332,
      "volume24hUsdEstimate": 2506.60784044001,
      "volume7dUsdEstimate": 9408.675876649155
    },
    "rebase-cwustc": {
      "baseOrStartSymbol": "REBASE",
      "currentHourId": 494514,
      "hourVolumeUsdEstimate": 0.0,
      "pairId": "rebase-cwustc",
      "pairType": "legacy",
      "quoteOrEndSymbol": "CWUSTC",
      "raw": {
        "hourVolumePrimary": 0.0,
        "hourVolumeSecondary": 0.0,
        "volume24hPrimary": 0.0,
        "volume24hSecondary": 0.0,
        "volume7dPrimary": 0.0,
        "volume7dSecondary": 0.0
      },
      "swapCount24h": 0,
      "swapCount7d": 0,
      "volume24hUsdEstimate": 0.0,
      "volume7dUsdEstimate": 0.0
    },
    "rebase-ustc": {
      "baseOrStartSymbol": "REBASE",
      "currentHourId": 494514,
      "hourVolumeUsdEstimate": 0.0,
      "pairId": "rebase-ustc",
      "pairType": "legacy",
      "quoteOrEndSymbol": "USTC",
      "raw": {
        "hourVolumePrimary": 0.0,
        "hourVolumeSecondary": 0.0,
        "volume24hPrimary": 14699.214848,
        "volume24hSecondary": 7932.235692,
        "volume7dPrimary": 246026.910584,
        "volume7dSecondary": 133561.421398
      },
      "swapCount24h": 39,
      "swapCount7d": 613,
      "volume24hUsdEstimate": 55.858565775993,
      "volume7dUsdEstimate": 940.535522642074
    },
    "weso-cwlunc": {
      "baseOrStartSymbol": "WESO",
      "currentHourId": 494514,
      "hourVolumeUsdEstimate": 0.0,
      "pairId": "weso-cwlunc",
      "pairType": "legacy",
      "quoteOrEndSymbol": "CWLUNC",
      "raw": {
        "hourVolumePrimary": 0.0,
        "hourVolumeSecondary": 0.0,
        "volume24hPrimary": 0.0,
        "volume24hSecondary": 0.0,
        "volume7dPrimary": 0.0,
        "volume7dSecondary": 0.0
      },
      "swapCount24h": 0,
      "swapCount7d": 0,
      "volume24hUsdEstimate": 0.0,
      "volume7dUsdEstimate": 0.0
    },
    "weso-lunc": {
      "baseOrStartSymbol": "WESO",
      "currentHourId": 494514,
      "hourVolumeUsdEstimate": 2.243428600825,
      "pairId": "weso-lunc",
      "pairType": "legacy",
      "quoteOrEndSymbol": "LUNC",
      "raw": {
        "hourVolumePrimary": 671.546845,
        "hourVolumeSecondary": 27173.311541,
        "volume24hPrimary": 61200.23084,
        "volume24hSecondary": 2473489.120827,
        "volume7dPrimary": 1614631.644965,
        "volume7dSecondary": 65564477.029998004
      },
      "swapCount24h": 121,
      "swapCount7d": 961,
      "volume24hUsdEstimate": 204.211261815477,
      "volume7dUsdEstimate": 5413.003223596635
    }
  },
  "prices": {
    "LUNC": 8.256e-05,
    "USTC": 0.00704197
  },
  "updatedAtIso": "2026-05-31T18:41:49.385339+00:00"
}