{
  "lastProcessedHeight": 29500436,
  "pairs": {
    "cwlunc-lunc": {
      "baseOrStartSymbol": "CWLUNC",
      "currentHourId": 495576,
      "hourVolumeUsdEstimate": 0.0,
      "pairId": "cwlunc-lunc",
      "pairType": "legacy",
      "quoteOrEndSymbol": "LUNC",
      "raw": {
        "hourVolumePrimary": 0.0,
        "hourVolumeSecondary": 0.0,
        "volume24hPrimary": 121368.319431,
        "volume24hSecondary": 120761.477833,
        "volume7dPrimary": 2064898.661537,
        "volume7dSecondary": 2054584.168225
      },
      "swapCount24h": 1,
      "swapCount7d": 11,
      "volume24hUsdEstimate": 7.76617063944,
      "volume7dUsdEstimate": 132.13030785855
    },
    "rebase-cwustc": {
      "baseOrStartSymbol": "REBASE",
      "currentHourId": 495576,
      "hourVolumeUsdEstimate": 0.0,
      "pairId": "rebase-cwustc",
      "pairType": "legacy",
      "quoteOrEndSymbol": "CWUSTC",
      "raw": {
        "hourVolumePrimary": 0.0,
        "hourVolumeSecondary": 0.0,
        "volume24hPrimary": 0.0,
        "volume24hSecondary": 0.0,
        "volume7dPrimary": 0.0,
        "volume7dSecondary": 0.0
      },
      "swapCount24h": 0,
      "swapCount7d": 0,
      "volume24hUsdEstimate": 0.0,
      "volume7dUsdEstimate": 0.0
    },
    "rebase-ustc": {
      "baseOrStartSymbol": "REBASE",
      "currentHourId": 495576,
      "hourVolumeUsdEstimate": 0.0,
      "pairId": "rebase-ustc",
      "pairType": "legacy",
      "quoteOrEndSymbol": "USTC",
      "raw": {
        "hourVolumePrimary": 0.0,
        "hourVolumeSecondary": 0.0,
        "volume24hPrimary": 0.0,
        "volume24hSecondary": 0.0,
        "volume7dPrimary": 0.0,
        "volume7dSecondary": 0.0
      },
      "swapCount24h": 0,
      "swapCount7d": 0,
      "volume24hUsdEstimate": 0.0,
      "volume7dUsdEstimate": 0.0
    },
    "weso-cwlunc": {
      "baseOrStartSymbol": "WESO",
      "currentHourId": 495576,
      "hourVolumeUsdEstimate": 0.0,
      "pairId": "weso-cwlunc",
      "pairType": "legacy",
      "quoteOrEndSymbol": "CWLUNC",
      "raw": {
        "hourVolumePrimary": 0.0,
        "hourVolumeSecondary": 0.0,
        "volume24hPrimary": 0.0,
        "volume24hSecondary": 0.0,
        "volume7dPrimary": 0.0,
        "volume7dSecondary": 0.0
      },
      "swapCount24h": 0,
      "swapCount7d": 0,
      "volume24hUsdEstimate": 0.0,
      "volume7dUsdEstimate": 0.0
    },
    "weso-lunc": {
      "baseOrStartSymbol": "WESO",
      "currentHourId": 495576,
      "hourVolumeUsdEstimate": 1.613257240549,
      "pairId": "weso-lunc",
      "pairType": "legacy",
      "quoteOrEndSymbol": "LUNC",
      "raw": {
        "hourVolumePrimary": 629.27141,
        "hourVolumeSecondary": 25085.635835,
        "volume24hPrimary": 62179.185277,
        "volume24hSecondary": 2482697.34793,
        "volume7dPrimary": 453040.955504,
        "volume7dSecondary": 18088653.383704
      },
      "swapCount24h": 137,
      "swapCount7d": 974,
      "volume24hUsdEstimate": 159.662266445378,
      "volume7dUsdEstimate": 1163.281299106004
    }
  },
  "prices": {
    "LUNC": 6.431e-05,
    "USTC": 0.00576748
  },
  "updatedAtIso": "2026-07-15T00:57:03.386107+00:00"
}