{
  "generatedAt": "2026-05-30T16:53:50.765Z",
  "wesoStatsSupply": 695375633.181248,
  "wesoStatsTotalSupply": 10000000000,
  "prices": {
    "LUNC": 0.00008039818324354094,
    "USTC": 0.006542415703703823,
    "AUTC": 0.00717103,
    "CATC": 0.00724375,
    "CHTC": 1.10694483,
    "CNTC": 0.0014778,
    "DKTC": 0.00155812,
    "EUTC": 0.64648997,
    "GBTC": 0.0134266,
    "HKTC": 0.00127623,
    "IDTC": 5.6e-7,
    "INTC": 0.00010526,
    "JPTC": 0.00006279,
    "KRTC": 0.00004264,
    "MNTC": 0.00005175,
    "MYTC": 0.00252207,
    "NOTC": 0.0010808,
    "PHTC": 0.00016241,
    "SDTC": 4.21879263,
    "SETC": 0.00108095,
    "SGTC": 0.00783024,
    "THTC": 0.0003075,
    "WESO": 0.003218306874771097,
    "REBASE": 0.0035230777716131014,
    "TERRA": 0.00193281,
    "FROG": 0.00000317,
    "ADDVOW": 0.0000186,
    "ALPHA": 0.00002073,
    "AMPLUNC": 0.00011123,
    "ART": 0.00003694,
    "ASTRO": 0.00058505,
    "BAKED": 3.75988464,
    "BLAME": 0.00002244,
    "BLEEVE": 0.00001249,
    "BLUNA": 0.0000711,
    "BOTS": 7e-8,
    "BTUSD": 0.47889815,
    "BULL": 0.00001331,
    "BURNIX": 0.0001115,
    "CATWIFHAT": 4e-8,
    "CBFC": 0.00014335,
    "CNIP": 0.00254315,
    "COFFEE": 0.00001528,
    "CRYSTAL": 0.0005728,
    "CTX": 0.29054042,
    "DO": 1.3e-9,
    "DOGE": 0.00099298,
    "ELPACO": 0.0026876,
    "FIRE": 4.5e-9,
    "FLX": 0.00000241,
    "FOOD": 2.9e-7,
    "FRG": 0.00065647,
    "FUN": 5.76891041,
    "FUTUREFLARE": 9.2e-7,
    "GRDX": 0.00167565,
    "HOTL": 0.00011029,
    "IDEV": 0.00062266,
    "JURASS": 0.000001,
    "JURIS": 0.00000265,
    "KENNY": 7.4e-7,
    "KNEEL": 0.00051016,
    "KRQ": 1.5e-7,
    "LCM": 1.9e-7,
    "LCW": 0.00038449,
    "LEAPE": 2e-10,
    "LENNYL": 1.1e-9,
    "LENNYR": 9e-10,
    "LIX": 0.00001345,
    "LTK": 0.00588301,
    "LTRN": 1e-7,
    "MBA": 0.00000381,
    "MIOFF": 2e-8,
    "MIR": 0.0073999,
    "NHERA": 3e-8,
    "POG": 1.7e-7,
    "QUID": 0.00015484,
    "ROTTI": 1e-8,
    "SAYVE": 5.3e-7,
    "SELE": 0.01597407,
    "SKI": 0.00010669,
    "SMF": 0.0000233,
    "SMT": 0.00008151,
    "TCR": 0.00005568,
    "TEAI": 1.2e-7,
    "TEST": 0.00008501,
    "THC": 7.9e-7,
    "TNEWS": 0.00000163,
    "ULC": 9.3e-7,
    "USTRIX": 0.3707097,
    "UWU": 0.000035,
    "VIMA": 0.00027702,
    "WAVAX": 17.87897218,
    "WETH": 1704.08776265,
    "MDOT": 1.1e-7,
    "CWLUNC": 0.00008039818324354094,
    "CWUSTC": 0.006542415703703823
  },
  "rows": [
    {
      "pairId": "amplunc-cwlunc",
      "type": "direct",
      "base": "AMPLUNC",
      "quote": "CWLUNC",
      "priceUsd": 0.000111,
      "marketCap": 14373.527289,
      "fdv": 14373.527289,
      "liquidity": 172.937155,
      "volume24h": 0,
      "volume7d": 0,
      "traders": 2,
      "volumeSource": "standard",
      "liquiditySource": "pool_tvl",
      "marketCapSource": "token_market_stats:cw20_token_info",
      "fdvSource": "token_market_stats:cw20_token_info",
      "tokenSupplySource": "cw20_token_info",
      "tokenPriceSource": "AMPLUNC"
    },
    {
      "pairId": "amplunc-cwustc",
      "type": "routed",
      "base": "AMPLUNC",
      "quote": "CWUSTC",
      "priceUsd": 0.000111,
      "marketCap": 14373.527289,
      "fdv": 14373.527289,
      "liquidity": 154.498199,
      "volume24h": 0,
      "volume7d": 0,
      "traders": 1,
      "volumeSource": "standard",
      "liquiditySource": "routed_estimate",
      "marketCapSource": "token_market_stats:cw20_token_info",
      "fdvSource": "token_market_stats:cw20_token_info",
      "tokenSupplySource": "cw20_token_info",
      "tokenPriceSource": "AMPLUNC"
    },
    {
      "pairId": "amplunc-lunc",
      "type": "routed",
      "base": "AMPLUNC",
      "quote": "LUNC",
      "priceUsd": 0.000111,
      "marketCap": 14373.527289,
      "fdv": 14373.527289,
      "liquidity": 172.937155,
      "volume24h": 0,
      "volume7d": 0,
      "traders": 3,
      "volumeSource": "standard",
      "liquiditySource": "routed_estimate",
      "marketCapSource": "token_market_stats:cw20_token_info",
      "fdvSource": "token_market_stats:cw20_token_info",
      "tokenSupplySource": "cw20_token_info",
      "tokenPriceSource": "AMPLUNC"
    },
    {
      "pairId": "amplunc-mdot",
      "type": "routed",
      "base": "AMPLUNC",
      "quote": "MDOT",
      "priceUsd": 0.000111,
      "marketCap": 14373.527289,
      "fdv": 14373.527289,
      "liquidity": 0.036679,
      "volume24h": 0,
      "volume7d": 0,
      "traders": 0,
      "volumeSource": "standard",
      "liquiditySource": "routed_estimate",
      "marketCapSource": "token_market_stats:cw20_token_info",
      "fdvSource": "token_market_stats:cw20_token_info",
      "tokenSupplySource": "cw20_token_info",
      "tokenPriceSource": "AMPLUNC"
    },
    {
      "pairId": "amplunc-ustc",
      "type": "routed",
      "base": "AMPLUNC",
      "quote": "USTC",
      "priceUsd": 0.000111,
      "marketCap": 14373.527289,
      "fdv": 14373.527289,
      "liquidity": 141.121989,
      "volume24h": 0,
      "volume7d": 0,
      "traders": 0,
      "volumeSource": "standard",
      "liquiditySource": "routed_estimate",
      "marketCapSource": "token_market_stats:cw20_token_info",
      "fdvSource": "token_market_stats:cw20_token_info",
      "tokenSupplySource": "cw20_token_info",
      "tokenPriceSource": "AMPLUNC"
    },
    {
      "pairId": "astro-amplunc",
      "type": "routed",
      "base": "ASTRO",
      "quote": "AMPLUNC",
      "priceUsd": 0.000585,
      "marketCap": 585049.999415,
      "fdv": 585049.999415,
      "liquidity": 0.058972,
      "volume24h": 0,
      "volume7d": 0,
      "traders": 1,
      "volumeSource": "standard",
      "liquiditySource": "routed_estimate",
      "marketCapSource": "token_market_stats:cw20_token_info",
      "fdvSource": "token_market_stats:cw20_token_info",
      "tokenSupplySource": "cw20_token_info",
      "tokenPriceSource": "ASTRO"
    },
    {
      "pairId": "astro-cwlunc",
      "type": "direct",
      "base": "ASTRO",
      "quote": "CWLUNC",
      "priceUsd": 0.000585,
      "marketCap": 585049.999415,
      "fdv": 585049.999415,
      "liquidity": 0.065779,
      "volume24h": 0,
      "volume7d": 0,
      "traders": 9,
      "volumeSource": "standard",
      "liquiditySource": "pool_tvl",
      "marketCapSource": "token_market_stats:cw20_token_info",
      "fdvSource": "token_market_stats:cw20_token_info",
      "tokenSupplySource": "cw20_token_info",
      "tokenPriceSource": "ASTRO"
    },
    {
      "pairId": "astro-cwustc",
      "type": "routed",
      "base": "ASTRO",
      "quote": "CWUSTC",
      "priceUsd": 0.000585,
      "marketCap": 585049.999415,
      "fdv": 585049.999415,
      "liquidity": 0.05721,
      "volume24h": 0,
      "volume7d": 0,
      "traders": 2,
      "volumeSource": "standard",
      "liquiditySource": "routed_estimate",
      "marketCapSource": "token_market_stats:cw20_token_info",
      "fdvSource": "token_market_stats:cw20_token_info",
      "tokenSupplySource": "cw20_token_info",
      "tokenPriceSource": "ASTRO"
    },
    {
      "pairId": "astro-lunc",
      "type": "routed",
      "base": "ASTRO",
      "quote": "LUNC",
      "priceUsd": 0.000585,
      "marketCap": 585049.999415,
      "fdv": 585049.999415,
      "liquidity": 0.065779,
      "volume24h": 0,
      "volume7d": 0,
      "traders": 8,
      "volumeSource": "standard",
      "liquiditySource": "routed_estimate",
      "marketCapSource": "token_market_stats:cw20_token_info",
      "fdvSource": "token_market_stats:cw20_token_info",
      "tokenSupplySource": "cw20_token_info",
      "tokenPriceSource": "ASTRO"
    },
    {
      "pairId": "astro-mdot",
      "type": "routed",
      "base": "ASTRO",
      "quote": "MDOT",
      "priceUsd": 0.000585,
      "marketCap": 585049.999415,
      "fdv": 585049.999415,
      "liquidity": 0.038941,
      "volume24h": 0,
      "volume7d": 0,
      "traders": 0,
      "volumeSource": "standard",
      "liquiditySource": "routed_estimate",
      "marketCapSource": "token_market_stats:cw20_token_info",
      "fdvSource": "token_market_stats:cw20_token_info",
      "tokenSupplySource": "cw20_token_info",
      "tokenPriceSource": "ASTRO"
    },
    {
      "pairId": "astro-ustc",
      "type": "routed",
      "base": "ASTRO",
      "quote": "USTC",
      "priceUsd": 0.000585,
      "marketCap": 585049.999415,
      "fdv": 585049.999415,
      "liquidity": 0.056989,
      "volume24h": 0,
      "volume7d": 0,
      "traders": 4,
      "volumeSource": "standard",
      "liquiditySource": "routed_estimate",
      "marketCapSource": "token_market_stats:cw20_token_info",
      "fdvSource": "token_market_stats:cw20_token_info",
      "tokenSupplySource": "cw20_token_info",
      "tokenPriceSource": "ASTRO"
    },
    {
      "pairId": "astro-wavax",
      "type": "routed",
      "base": "ASTRO",
      "quote": "WAVAX",
      "priceUsd": 0.000585,
      "marketCap": 585049.999415,
      "fdv": 585049.999415,
      "liquidity": 0.056406,
      "volume24h": 0,
      "volume7d": 0,
      "traders": 2,
      "volumeSource": "standard",
      "liquiditySource": "routed_estimate",
      "marketCapSource": "token_market_stats:cw20_token_info",
      "fdvSource": "token_market_stats:cw20_token_info",
      "tokenSupplySource": "cw20_token_info",
      "tokenPriceSource": "ASTRO"
    },
    {
      "pairId": "autc-lunc",
      "type": "direct",
      "base": "AUTC",
      "quote": "LUNC",
      "priceUsd": 0.007171,
      "marketCap": 4986559.526812,
      "fdv": 71710300,
      "liquidity": "",
      "volume24h": null,
      "volume7d": null,
      "traders": null,
      "volumeSource": "missing",
      "liquiditySource": "missing",
      "marketCapSource": "frontend_stats_supply_x_base_price",
      "fdvSource": "frontend_stats_totalSupply_x_base_price",
      "tokenSupplySource": "legacy_fallback",
      "tokenPriceSource": "audit_price_map"
    },
    {
      "pairId": "catc-lunc",
      "type": "direct",
      "base": "CATC",
      "quote": "LUNC",
      "priceUsd": 0.007244,
      "marketCap": 5037127.242857,
      "fdv": 72437500,
      "liquidity": "",
      "volume24h": null,
      "volume7d": null,
      "traders": null,
      "volumeSource": "missing",
      "liquiditySource": "missing",
      "marketCapSource": "frontend_stats_supply_x_base_price",
      "fdvSource": "frontend_stats_totalSupply_x_base_price",
      "tokenSupplySource": "legacy_fallback",
      "tokenPriceSource": "audit_price_map"
    },
    {
      "pairId": "chtc-lunc",
      "type": "direct",
      "base": "CHTC",
      "quote": "LUNC",
      "priceUsd": 1.106945,
      "marketCap": 769742462.057959,
      "fdv": 11069448300,
      "liquidity": "",
      "volume24h": null,
      "volume7d": null,
      "traders": null,
      "volumeSource": "missing",
      "liquiditySource": "missing",
      "marketCapSource": "frontend_stats_supply_x_base_price",
      "fdvSource": "frontend_stats_totalSupply_x_base_price",
      "tokenSupplySource": "legacy_fallback",
      "tokenPriceSource": "audit_price_map"
    },
    {
      "pairId": "cntc-lunc",
      "type": "direct",
      "base": "CNTC",
      "quote": "LUNC",
      "priceUsd": 0.001478,
      "marketCap": 1027626.110715,
      "fdv": 14778000,
      "liquidity": "",
      "volume24h": null,
      "volume7d": null,
      "traders": null,
      "volumeSource": "missing",
      "liquiditySource": "missing",
      "marketCapSource": "frontend_stats_supply_x_base_price",
      "fdvSource": "frontend_stats_totalSupply_x_base_price",
      "tokenSupplySource": "legacy_fallback",
      "tokenPriceSource": "audit_price_map"
    },
    {
      "pairId": "cwlunc-cwustc",
      "type": "direct",
      "base": "CWLUNC",
      "quote": "CWUSTC",
      "priceUsd": 0.00008,
      "marketCap": 80404820.712351,
      "fdv": 80404820.712351,
      "liquidity": 1993.899341,
      "volume24h": 38.819867244658,
      "volume7d": 1955.927122097281,
      "traders": 11,
      "volumeSource": "standard",
      "liquiditySource": "pool_tvl",
      "marketCapSource": "token_market_stats:cw20_token_info",
      "fdvSource": "token_market_stats:cw20_token_info",
      "tokenSupplySource": "cw20_token_info",
      "tokenPriceSource": "CWLUNC"
    },
    {
      "pairId": "cwlunc-lunc",
      "type": "direct",
      "base": "CWLUNC",
      "quote": "LUNC",
      "priceUsd": 0.00008,
      "marketCap": 80404820.712351,
      "fdv": 80404820.712351,
      "liquidity": 18942.293287,
      "volume24h": 368.136593268353,
      "volume7d": 6762.985426854937,
      "traders": 49,
      "volumeSource": "legacy",
      "liquiditySource": "native_reserve",
      "marketCapSource": "token_market_stats:cw20_token_info",
      "fdvSource": "token_market_stats:cw20_token_info",
      "tokenSupplySource": "cw20_token_info",
      "tokenPriceSource": "CWLUNC"
    },
    {
      "pairId": "cwustc-lunc",
      "type": "routed",
      "base": "CWUSTC",
      "quote": "LUNC",
      "priceUsd": 0.006542,
      "marketCap": 6542415.703704,
      "fdv": 6542415.703704,
      "liquidity": 1993.899341,
      "volume24h": 0,
      "volume7d": 0,
      "traders": 5,
      "volumeSource": "standard",
      "liquiditySource": "routed_estimate",
      "marketCapSource": "token_market_stats:cw20_token_info",
      "fdvSource": "token_market_stats:cw20_token_info",
      "tokenSupplySource": "cw20_token_info",
      "tokenPriceSource": "CWUSTC"
    },
    {
      "pairId": "cwustc-ustc",
      "type": "direct",
      "base": "CWUSTC",
      "quote": "USTC",
      "priceUsd": 0.006542,
      "marketCap": 6542415.703704,
      "fdv": 6542415.703704,
      "liquidity": 11765.208517,
      "volume24h": 3.308360017417,
      "volume7d": 1797.367276482414,
      "traders": 28,
      "volumeSource": "standard",
      "liquiditySource": "native_reserve",
      "marketCapSource": "token_market_stats:cw20_token_info",
      "fdvSource": "token_market_stats:cw20_token_info",
      "tokenSupplySource": "cw20_token_info",
      "tokenPriceSource": "CWUSTC"
    },
    {
      "pairId": "dktc-lunc",
      "type": "direct",
      "base": "DKTC",
      "quote": "LUNC",
      "priceUsd": 0.001558,
      "marketCap": 1083478.681572,
      "fdv": 15581200,
      "liquidity": "",
      "volume24h": null,
      "volume7d": null,
      "traders": null,
      "volumeSource": "missing",
      "liquiditySource": "missing",
      "marketCapSource": "frontend_stats_supply_x_base_price",
      "fdvSource": "frontend_stats_totalSupply_x_base_price",
      "tokenSupplySource": "legacy_fallback",
      "tokenPriceSource": "audit_price_map"
    },
    {
      "pairId": "eutc-lunc",
      "type": "direct",
      "base": "EUTC",
      "quote": "LUNC",
      "priceUsd": 0.64649,
      "marketCap": 449553372.234076,
      "fdv": 6464899700,
      "liquidity": "",
      "volume24h": null,
      "volume7d": null,
      "traders": null,
      "volumeSource": "missing",
      "liquiditySource": "missing",
      "marketCapSource": "frontend_stats_supply_x_base_price",
      "fdvSource": "frontend_stats_totalSupply_x_base_price",
      "tokenSupplySource": "legacy_fallback",
      "tokenPriceSource": "audit_price_map"
    },
    {
      "pairId": "gbtc-lunc",
      "type": "direct",
      "base": "GBTC",
      "quote": "LUNC",
      "priceUsd": 0.013427,
      "marketCap": 9336530.476471,
      "fdv": 134266000,
      "liquidity": "",
      "volume24h": null,
      "volume7d": null,
      "traders": null,
      "volumeSource": "missing",
      "liquiditySource": "missing",
      "marketCapSource": "frontend_stats_supply_x_base_price",
      "fdvSource": "frontend_stats_totalSupply_x_base_price",
      "tokenSupplySource": "legacy_fallback",
      "tokenPriceSource": "audit_price_map"
    },
    {
      "pairId": "hktc-lunc",
      "type": "direct",
      "base": "HKTC",
      "quote": "LUNC",
      "priceUsd": 0.001276,
      "marketCap": 887459.244335,
      "fdv": 12762300,
      "liquidity": "",
      "volume24h": null,
      "volume7d": null,
      "traders": null,
      "volumeSource": "missing",
      "liquiditySource": "missing",
      "marketCapSource": "frontend_stats_supply_x_base_price",
      "fdvSource": "frontend_stats_totalSupply_x_base_price",
      "tokenSupplySource": "legacy_fallback",
      "tokenPriceSource": "audit_price_map"
    },
    {
      "pairId": "idtc-lunc",
      "type": "direct",
      "base": "IDTC",
      "quote": "LUNC",
      "priceUsd": 0.000001,
      "marketCap": 389.410355,
      "fdv": 5600,
      "liquidity": "",
      "volume24h": null,
      "volume7d": null,
      "traders": null,
      "volumeSource": "missing",
      "liquiditySource": "missing",
      "marketCapSource": "frontend_stats_supply_x_base_price",
      "fdvSource": "frontend_stats_totalSupply_x_base_price",
      "tokenSupplySource": "legacy_fallback",
      "tokenPriceSource": "audit_price_map"
    },
    {
      "pairId": "intc-lunc",
      "type": "direct",
      "base": "INTC",
      "quote": "LUNC",
      "priceUsd": 0.000105,
      "marketCap": 73195.239149,
      "fdv": 1052600,
      "liquidity": "",
      "volume24h": null,
      "volume7d": null,
      "traders": null,
      "volumeSource": "missing",
      "liquiditySource": "missing",
      "marketCapSource": "frontend_stats_supply_x_base_price",
      "fdvSource": "frontend_stats_totalSupply_x_base_price",
      "tokenSupplySource": "legacy_fallback",
      "tokenPriceSource": "audit_price_map"
    },
    {
      "pairId": "jptc-lunc",
      "type": "direct",
      "base": "JPTC",
      "quote": "LUNC",
      "priceUsd": 0.000063,
      "marketCap": 43662.636007,
      "fdv": 627900,
      "liquidity": "",
      "volume24h": null,
      "volume7d": null,
      "traders": null,
      "volumeSource": "missing",
      "liquiditySource": "missing",
      "marketCapSource": "frontend_stats_supply_x_base_price",
      "fdvSource": "frontend_stats_totalSupply_x_base_price",
      "tokenSupplySource": "legacy_fallback",
      "tokenPriceSource": "audit_price_map"
    },
    {
      "pairId": "krtc-lunc",
      "type": "direct",
      "base": "KRTC",
      "quote": "LUNC",
      "priceUsd": 0.000043,
      "marketCap": 29650.816999,
      "fdv": 426400,
      "liquidity": "",
      "volume24h": null,
      "volume7d": null,
      "traders": null,
      "volumeSource": "missing",
      "liquiditySource": "missing",
      "marketCapSource": "frontend_stats_supply_x_base_price",
      "fdvSource": "frontend_stats_totalSupply_x_base_price",
      "tokenSupplySource": "legacy_fallback",
      "tokenPriceSource": "audit_price_map"
    },
    {
      "pairId": "mdot-cwlunc",
      "type": "direct",
      "base": "MDOT",
      "quote": "CWLUNC",
      "priceUsd": 0,
      "marketCap": 2.272804,
      "fdv": 2.272804,
      "liquidity": 0.044948,
      "volume24h": 0,
      "volume7d": 0,
      "traders": 2,
      "volumeSource": "standard",
      "liquiditySource": "pool_tvl",
      "marketCapSource": "token_market_stats:cw20_token_info",
      "fdvSource": "token_market_stats:cw20_token_info",
      "tokenSupplySource": "cw20_token_info",
      "tokenPriceSource": "MDOT"
    },
    {
      "pairId": "mdot-cwustc",
      "type": "routed",
      "base": "MDOT",
      "quote": "CWUSTC",
      "priceUsd": 0,
      "marketCap": 2.272804,
      "fdv": 2.272804,
      "liquidity": 0.039154,
      "volume24h": 0,
      "volume7d": 0,
      "traders": 1,
      "volumeSource": "standard",
      "liquiditySource": "routed_estimate",
      "marketCapSource": "token_market_stats:cw20_token_info",
      "fdvSource": "token_market_stats:cw20_token_info",
      "tokenSupplySource": "cw20_token_info",
      "tokenPriceSource": "MDOT"
    },
    {
      "pairId": "mdot-lunc",
      "type": "routed",
      "base": "MDOT",
      "quote": "LUNC",
      "priceUsd": 0,
      "marketCap": 2.272804,
      "fdv": 2.272804,
      "liquidity": 0.044948,
      "volume24h": 0,
      "volume7d": 0,
      "traders": 0,
      "volumeSource": "standard",
      "liquiditySource": "routed_estimate",
      "marketCapSource": "token_market_stats:cw20_token_info",
      "fdvSource": "token_market_stats:cw20_token_info",
      "tokenSupplySource": "cw20_token_info",
      "tokenPriceSource": "MDOT"
    },
    {
      "pairId": "mdot-rebase",
      "type": "routed",
      "base": "MDOT",
      "quote": "REBASE",
      "priceUsd": 0,
      "marketCap": 2.272804,
      "fdv": 2.272804,
      "liquidity": 0.037637,
      "volume24h": 0,
      "volume7d": 0,
      "traders": 0,
      "volumeSource": "standard",
      "liquiditySource": "routed_estimate",
      "marketCapSource": "token_market_stats:cw20_token_info",
      "fdvSource": "token_market_stats:cw20_token_info",
      "tokenSupplySource": "cw20_token_info",
      "tokenPriceSource": "MDOT"
    },
    {
      "pairId": "mdot-ustc",
      "type": "routed",
      "base": "MDOT",
      "quote": "USTC",
      "priceUsd": 0,
      "marketCap": 2.272804,
      "fdv": 2.272804,
      "liquidity": 0.036334,
      "volume24h": 0,
      "volume7d": 0.51899441486,
      "traders": 2,
      "volumeSource": "standard",
      "liquiditySource": "routed_estimate",
      "marketCapSource": "token_market_stats:cw20_token_info",
      "fdvSource": "token_market_stats:cw20_token_info",
      "tokenSupplySource": "cw20_token_info",
      "tokenPriceSource": "MDOT"
    },
    {
      "pairId": "mdot-wavax",
      "type": "routed",
      "base": "MDOT",
      "quote": "WAVAX",
      "priceUsd": 0,
      "marketCap": 2.272804,
      "fdv": 2.272804,
      "liquidity": 0.038627,
      "volume24h": 0,
      "volume7d": 0,
      "traders": 0,
      "volumeSource": "standard",
      "liquiditySource": "routed_estimate",
      "marketCapSource": "token_market_stats:cw20_token_info",
      "fdvSource": "token_market_stats:cw20_token_info",
      "tokenSupplySource": "cw20_token_info",
      "tokenPriceSource": "MDOT"
    },
    {
      "pairId": "mdot-weso",
      "type": "routed",
      "base": "MDOT",
      "quote": "WESO",
      "priceUsd": 0,
      "marketCap": 2.272804,
      "fdv": 2.272804,
      "liquidity": 0.036334,
      "volume24h": 0,
      "volume7d": 0,
      "traders": 0,
      "volumeSource": "standard",
      "liquiditySource": "routed_estimate",
      "marketCapSource": "token_market_stats:cw20_token_info",
      "fdvSource": "token_market_stats:cw20_token_info",
      "tokenSupplySource": "cw20_token_info",
      "tokenPriceSource": "MDOT"
    },
    {
      "pairId": "mytc-lunc",
      "type": "direct",
      "base": "MYTC",
      "quote": "LUNC",
      "priceUsd": 0.002522,
      "marketCap": 1753786.023177,
      "fdv": 25220700,
      "liquidity": "",
      "volume24h": null,
      "volume7d": null,
      "traders": null,
      "volumeSource": "missing",
      "liquiditySource": "missing",
      "marketCapSource": "frontend_stats_supply_x_base_price",
      "fdvSource": "frontend_stats_totalSupply_x_base_price",
      "tokenSupplySource": "legacy_fallback",
      "tokenPriceSource": "audit_price_map"
    },
    {
      "pairId": "phtc-lunc",
      "type": "direct",
      "base": "PHTC",
      "quote": "LUNC",
      "priceUsd": 0.000162,
      "marketCap": 112935.956585,
      "fdv": 1624100,
      "liquidity": "",
      "volume24h": null,
      "volume7d": null,
      "traders": null,
      "volumeSource": "missing",
      "liquiditySource": "missing",
      "marketCapSource": "frontend_stats_supply_x_base_price",
      "fdvSource": "frontend_stats_totalSupply_x_base_price",
      "tokenSupplySource": "legacy_fallback",
      "tokenPriceSource": "audit_price_map"
    },
    {
      "pairId": "rebase-amplunc",
      "type": "routed",
      "base": "REBASE",
      "quote": "AMPLUNC",
      "priceUsd": 0.003523,
      "marketCap": 138642.554842,
      "fdv": 704615.554323,
      "liquidity": 138.864333,
      "volume24h": 0,
      "volume7d": 0,
      "traders": 0,
      "volumeSource": "standard",
      "liquiditySource": "routed_estimate",
      "marketCapSource": "token_market_stats:rebase_curve_plus_override",
      "fdvSource": "token_market_stats:rebase_curve_plus_override",
      "tokenSupplySource": "rebase_curve_plus_override",
      "tokenPriceSource": "REBASE"
    },
    {
      "pairId": "rebase-astro",
      "type": "routed",
      "base": "REBASE",
      "quote": "ASTRO",
      "priceUsd": 0.003523,
      "marketCap": 138642.554842,
      "fdv": 704615.554323,
      "liquidity": 0.057841,
      "volume24h": 0,
      "volume7d": 0,
      "traders": 0,
      "volumeSource": "standard",
      "liquiditySource": "routed_estimate",
      "marketCapSource": "token_market_stats:rebase_curve_plus_override",
      "fdvSource": "token_market_stats:rebase_curve_plus_override",
      "tokenSupplySource": "rebase_curve_plus_override",
      "tokenPriceSource": "REBASE"
    },
    {
      "pairId": "rebase-cwlunc",
      "type": "routed",
      "base": "REBASE",
      "quote": "CWLUNC",
      "priceUsd": 0.003523,
      "marketCap": 138642.554842,
      "fdv": 704615.554323,
      "liquidity": 1709.647071,
      "volume24h": 0,
      "volume7d": 0,
      "traders": 2,
      "volumeSource": "standard",
      "liquiditySource": "routed_estimate",
      "marketCapSource": "token_market_stats:rebase_curve_plus_override",
      "fdvSource": "token_market_stats:rebase_curve_plus_override",
      "tokenSupplySource": "rebase_curve_plus_override",
      "tokenPriceSource": "REBASE"
    },
    {
      "pairId": "rebase-cwustc",
      "type": "direct",
      "base": "REBASE",
      "quote": "CWUSTC",
      "priceUsd": 0.003523,
      "marketCap": 138642.554842,
      "fdv": 704615.554323,
      "liquidity": 3914.391816,
      "volume24h": 0,
      "volume7d": 0,
      "traders": 159,
      "volumeSource": "legacy",
      "liquiditySource": "placeholder_ratio_from:rebase-ustc",
      "marketCapSource": "token_market_stats:rebase_curve_plus_override",
      "fdvSource": "token_market_stats:rebase_curve_plus_override",
      "tokenSupplySource": "rebase_curve_plus_override",
      "tokenPriceSource": "REBASE"
    },
    {
      "pairId": "rebase-lunc",
      "type": "routed",
      "base": "REBASE",
      "quote": "LUNC",
      "priceUsd": 0.003523,
      "marketCap": 138642.554842,
      "fdv": 704615.554323,
      "liquidity": 1702.120349,
      "volume24h": 0,
      "volume7d": 0,
      "traders": 4,
      "volumeSource": "standard",
      "liquiditySource": "routed_estimate",
      "marketCapSource": "token_market_stats:rebase_curve_plus_override",
      "fdvSource": "token_market_stats:rebase_curve_plus_override",
      "tokenSupplySource": "rebase_curve_plus_override",
      "tokenPriceSource": "REBASE"
    },
    {
      "pairId": "rebase-ustc",
      "type": "direct",
      "base": "REBASE",
      "quote": "USTC",
      "priceUsd": 0.003523,
      "marketCap": 138642.554842,
      "fdv": 704615.554323,
      "liquidity": 23025.834209,
      "volume24h": 80.081960452695,
      "volume7d": 981.963654006613,
      "traders": 159,
      "volumeSource": "legacy",
      "liquiditySource": "native_reserve",
      "marketCapSource": "token_market_stats:rebase_curve_plus_override",
      "fdvSource": "token_market_stats:rebase_curve_plus_override",
      "tokenSupplySource": "rebase_curve_plus_override",
      "tokenPriceSource": "REBASE"
    },
    {
      "pairId": "rebase-wavax",
      "type": "routed",
      "base": "REBASE",
      "quote": "WAVAX",
      "priceUsd": 0.003523,
      "marketCap": 138642.554842,
      "fdv": 704615.554323,
      "liquidity": 9.321027,
      "volume24h": 0,
      "volume7d": 0,
      "traders": 0,
      "volumeSource": "standard",
      "liquiditySource": "routed_estimate",
      "marketCapSource": "token_market_stats:rebase_curve_plus_override",
      "fdvSource": "token_market_stats:rebase_curve_plus_override",
      "tokenSupplySource": "rebase_curve_plus_override",
      "tokenPriceSource": "REBASE"
    },
    {
      "pairId": "sdtc-lunc",
      "type": "direct",
      "base": "SDTC",
      "quote": "LUNC",
      "priceUsd": 4.218793,
      "marketCap": 2933645596.346632,
      "fdv": 42187926300,
      "liquidity": "",
      "volume24h": null,
      "volume7d": null,
      "traders": null,
      "volumeSource": "missing",
      "liquiditySource": "missing",
      "marketCapSource": "frontend_stats_supply_x_base_price",
      "fdvSource": "frontend_stats_totalSupply_x_base_price",
      "tokenSupplySource": "legacy_fallback",
      "tokenPriceSource": "audit_price_map"
    },
    {
      "pairId": "setc-lunc",
      "type": "direct",
      "base": "SETC",
      "quote": "LUNC",
      "priceUsd": 0.001081,
      "marketCap": 751666.290687,
      "fdv": 10809500,
      "liquidity": "",
      "volume24h": null,
      "volume7d": null,
      "traders": null,
      "volumeSource": "missing",
      "liquiditySource": "missing",
      "marketCapSource": "frontend_stats_supply_x_base_price",
      "fdvSource": "frontend_stats_totalSupply_x_base_price",
      "tokenSupplySource": "legacy_fallback",
      "tokenPriceSource": "audit_price_map"
    },
    {
      "pairId": "sgtc-lunc",
      "type": "direct",
      "base": "SGTC",
      "quote": "LUNC",
      "priceUsd": 0.00783,
      "marketCap": 5444958.097961,
      "fdv": 78302400,
      "liquidity": "",
      "volume24h": null,
      "volume7d": null,
      "traders": null,
      "volumeSource": "missing",
      "liquiditySource": "missing",
      "marketCapSource": "frontend_stats_supply_x_base_price",
      "fdvSource": "frontend_stats_totalSupply_x_base_price",
      "tokenSupplySource": "legacy_fallback",
      "tokenPriceSource": "audit_price_map"
    },
    {
      "pairId": "thtc-lunc",
      "type": "direct",
      "base": "THTC",
      "quote": "LUNC",
      "priceUsd": 0.000307,
      "marketCap": 213828.007203,
      "fdv": 3075000,
      "liquidity": "",
      "volume24h": null,
      "volume7d": null,
      "traders": null,
      "volumeSource": "missing",
      "liquiditySource": "missing",
      "marketCapSource": "frontend_stats_supply_x_base_price",
      "fdvSource": "frontend_stats_totalSupply_x_base_price",
      "tokenSupplySource": "legacy_fallback",
      "tokenPriceSource": "audit_price_map"
    },
    {
      "pairId": "ustc-cwlunc",
      "type": "routed",
      "base": "USTC",
      "quote": "CWLUNC",
      "priceUsd": 0.00008,
      "marketCap": 80404820.712351,
      "fdv": 80404820.712351,
      "liquidity": 1993.899341,
      "volume24h": 0,
      "volume7d": 0,
      "traders": 3,
      "volumeSource": "standard",
      "liquiditySource": "routed_estimate",
      "marketCapSource": "token_market_stats:cw20_token_info",
      "fdvSource": "token_market_stats:cw20_token_info",
      "tokenSupplySource": "cw20_token_info",
      "tokenPriceSource": "CWLUNC"
    },
    {
      "pairId": "ustc-lunc",
      "type": "direct",
      "base": "USTC",
      "quote": "LUNC",
      "priceUsd": 0.006542,
      "marketCap": 519271503.271462,
      "fdv": 519271503.271462,
      "liquidity": 1993.899341,
      "volume24h": 30.953386193084,
      "volume7d": 1896.623988042763,
      "traders": 32,
      "volumeSource": "standard",
      "liquiditySource": "routed_estimate",
      "marketCapSource": "token_market_stats:native_bank_supply",
      "fdvSource": "token_market_stats:native_bank_supply",
      "tokenSupplySource": "native_bank_supply",
      "tokenPriceSource": "USTC"
    },
    {
      "pairId": "wavax-amplunc",
      "type": "routed",
      "base": "WAVAX",
      "quote": "AMPLUNC",
      "priceUsd": 17.878972,
      "marketCap": 8176.288235,
      "fdv": 8176.288235,
      "liquidity": 9.860566,
      "volume24h": 0,
      "volume7d": 0,
      "traders": 1,
      "volumeSource": "standard",
      "liquiditySource": "routed_estimate",
      "marketCapSource": "token_market_stats:cw20_token_info",
      "fdvSource": "token_market_stats:cw20_token_info",
      "tokenSupplySource": "cw20_token_info",
      "tokenPriceSource": "WAVAX"
    },
    {
      "pairId": "wavax-cwlunc",
      "type": "direct",
      "base": "WAVAX",
      "quote": "CWLUNC",
      "priceUsd": 17.878972,
      "marketCap": 8176.288235,
      "fdv": 8176.288235,
      "liquidity": 10.993129,
      "volume24h": 0,
      "volume7d": 0,
      "traders": 6,
      "volumeSource": "standard",
      "liquiditySource": "pool_tvl",
      "marketCapSource": "token_market_stats:cw20_token_info",
      "fdvSource": "token_market_stats:cw20_token_info",
      "tokenSupplySource": "cw20_token_info",
      "tokenPriceSource": "WAVAX"
    },
    {
      "pairId": "wavax-cwustc",
      "type": "routed",
      "base": "WAVAX",
      "quote": "CWUSTC",
      "priceUsd": 17.878972,
      "marketCap": 8176.288235,
      "fdv": 8176.288235,
      "liquidity": 8.844435,
      "volume24h": 0,
      "volume7d": 0,
      "traders": 0,
      "volumeSource": "standard",
      "liquiditySource": "routed_estimate",
      "marketCapSource": "token_market_stats:cw20_token_info",
      "fdvSource": "token_market_stats:cw20_token_info",
      "tokenSupplySource": "cw20_token_info",
      "tokenPriceSource": "WAVAX"
    },
    {
      "pairId": "wavax-lunc",
      "type": "routed",
      "base": "WAVAX",
      "quote": "LUNC",
      "priceUsd": 17.878972,
      "marketCap": 8176.288235,
      "fdv": 8176.288235,
      "liquidity": 10.993129,
      "volume24h": 0,
      "volume7d": 0,
      "traders": 2,
      "volumeSource": "standard",
      "liquiditySource": "routed_estimate",
      "marketCapSource": "token_market_stats:cw20_token_info",
      "fdvSource": "token_market_stats:cw20_token_info",
      "tokenSupplySource": "cw20_token_info",
      "tokenPriceSource": "WAVAX"
    },
    {
      "pairId": "wavax-ustc",
      "type": "routed",
      "base": "WAVAX",
      "quote": "USTC",
      "priceUsd": 17.878972,
      "marketCap": 8176.288235,
      "fdv": 8176.288235,
      "liquidity": 9.268637,
      "volume24h": 0,
      "volume7d": 0,
      "traders": 1,
      "volumeSource": "standard",
      "liquiditySource": "routed_estimate",
      "marketCapSource": "token_market_stats:cw20_token_info",
      "fdvSource": "token_market_stats:cw20_token_info",
      "tokenSupplySource": "cw20_token_info",
      "tokenPriceSource": "WAVAX"
    },
    {
      "pairId": "weso-amplunc",
      "type": "routed",
      "base": "WESO",
      "quote": "AMPLUNC",
      "priceUsd": 0.003218,
      "marketCap": 2237932.180816,
      "fdv": 32183068.747711,
      "liquidity": 141.122175,
      "volume24h": 0,
      "volume7d": 0,
      "traders": 1,
      "volumeSource": "standard",
      "liquiditySource": "routed_estimate",
      "marketCapSource": "token_market_stats:weso_curve",
      "fdvSource": "token_market_stats:weso_curve",
      "tokenSupplySource": "weso_curve",
      "tokenPriceSource": "WESO"
    },
    {
      "pairId": "weso-astro",
      "type": "routed",
      "base": "WESO",
      "quote": "ASTRO",
      "priceUsd": 0.003218,
      "marketCap": 2237932.180816,
      "fdv": 32183068.747711,
      "liquidity": 0.056989,
      "volume24h": 0,
      "volume7d": 0,
      "traders": 1,
      "volumeSource": "standard",
      "liquiditySource": "routed_estimate",
      "marketCapSource": "token_market_stats:weso_curve",
      "fdvSource": "token_market_stats:weso_curve",
      "tokenSupplySource": "weso_curve",
      "tokenPriceSource": "WESO"
    },
    {
      "pairId": "weso-cwlunc",
      "type": "direct",
      "base": "WESO",
      "quote": "CWLUNC",
      "priceUsd": 0.003218,
      "marketCap": 2237932.180816,
      "fdv": 32183068.747711,
      "liquidity": 6390.711129,
      "volume24h": 0,
      "volume7d": 0,
      "traders": 199,
      "volumeSource": "legacy",
      "liquiditySource": "placeholder_ratio_from:weso-lunc",
      "marketCapSource": "token_market_stats:weso_curve",
      "fdvSource": "token_market_stats:weso_curve",
      "tokenSupplySource": "weso_curve",
      "tokenPriceSource": "WESO"
    },
    {
      "pairId": "weso-cwustc",
      "type": "routed",
      "base": "WESO",
      "quote": "CWUSTC",
      "priceUsd": 0.003218,
      "marketCap": 2237932.180816,
      "fdv": 32183068.747711,
      "liquidity": 1736.914327,
      "volume24h": 0,
      "volume7d": 0,
      "traders": 1,
      "volumeSource": "standard",
      "liquiditySource": "routed_estimate",
      "marketCapSource": "token_market_stats:weso_curve",
      "fdvSource": "token_market_stats:weso_curve",
      "tokenSupplySource": "weso_curve",
      "tokenPriceSource": "WESO"
    },
    {
      "pairId": "weso-lunc",
      "type": "direct",
      "base": "WESO",
      "quote": "LUNC",
      "priceUsd": 0.003218,
      "marketCap": 2237932.180816,
      "fdv": 32183068.747711,
      "liquidity": 91295.873274,
      "volume24h": 220.392055208285,
      "volume7d": 5350.759164225557,
      "traders": 199,
      "volumeSource": "legacy",
      "liquiditySource": "native_reserve",
      "marketCapSource": "token_market_stats:weso_curve",
      "fdvSource": "token_market_stats:weso_curve",
      "tokenSupplySource": "weso_curve",
      "tokenPriceSource": "WESO"
    },
    {
      "pairId": "weso-rebase",
      "type": "routed",
      "base": "WESO",
      "quote": "REBASE",
      "priceUsd": 0.003218,
      "marketCap": 2237932.180816,
      "fdv": 32183068.747711,
      "liquidity": 1746.134734,
      "volume24h": 0,
      "volume7d": 0,
      "traders": 5,
      "volumeSource": "standard",
      "liquiditySource": "routed_estimate",
      "marketCapSource": "token_market_stats:weso_curve",
      "fdvSource": "token_market_stats:weso_curve",
      "tokenSupplySource": "weso_curve",
      "tokenPriceSource": "WESO"
    },
    {
      "pairId": "weso-ustc",
      "type": "routed",
      "base": "WESO",
      "quote": "USTC",
      "priceUsd": 0.003218,
      "marketCap": 2237932.180816,
      "fdv": 32183068.747711,
      "liquidity": 1739.396275,
      "volume24h": 0,
      "volume7d": 0,
      "traders": 2,
      "volumeSource": "standard",
      "liquiditySource": "routed_estimate",
      "marketCapSource": "token_market_stats:weso_curve",
      "fdvSource": "token_market_stats:weso_curve",
      "tokenSupplySource": "weso_curve",
      "tokenPriceSource": "WESO"
    },
    {
      "pairId": "weso-wavax",
      "type": "routed",
      "base": "WESO",
      "quote": "WAVAX",
      "priceUsd": 0.003218,
      "marketCap": 2237932.180816,
      "fdv": 32183068.747711,
      "liquidity": 9.443949,
      "volume24h": 0,
      "volume7d": 0,
      "traders": 2,
      "volumeSource": "standard",
      "liquiditySource": "routed_estimate",
      "marketCapSource": "token_market_stats:weso_curve",
      "fdvSource": "token_market_stats:weso_curve",
      "tokenSupplySource": "weso_curve",
      "tokenPriceSource": "WESO"
    }
  ]
}
