{
  "generatedAt": "2026-05-28T01:34:50.194Z",
  "wesoStatsSupply": 694279274.19983,
  "wesoStatsTotalSupply": 10000000000,
  "prices": {
    "LUNC": 0.00008596487729530263,
    "USTC": 0.00626517152611408,
    "AUTC": 0.00713012,
    "CATC": 0.00722857,
    "CHTC": 1.0302752,
    "CNTC": 0.00147447,
    "DKTC": 0.00155729,
    "EUTC": 0.74683746,
    "GBTC": 0.0134349,
    "HKTC": 0.00127636,
    "IDTC": 5.6e-7,
    "INTC": 0.0001045,
    "JPTC": 0.00006273,
    "KRTC": 0.00004716,
    "MNTC": 0.00005547,
    "MYTC": 0.00252207,
    "NOTC": 0.0010778,
    "PHTC": 0.00016272,
    "SDTC": 4.52211649,
    "SETC": 0.00107855,
    "SGTC": 0.00782656,
    "THTC": 0.00030656,
    "WESO": 0.003425321513003569,
    "REBASE": 0.003374177042275525,
    "TERRA": 0.00192057,
    "FROG": 0.00000331,
    "ADDVOW": 0.00001994,
    "ALPHA": 0.00001931,
    "AMPLUNC": 0.00011093,
    "ART": 0.00003407,
    "ASTRO": 0.00054468,
    "BAKED": 4.02989145,
    "BLAME": 0.00003135,
    "BLEEVE": 0.00001351,
    "BLUNA": 0.00006618,
    "BOTS": 7e-8,
    "BTUSD": 0.44572852,
    "BULL": 0.00001319,
    "BURNIX": 0.00010963,
    "CATWIFHAT": 3e-8,
    "CBFC": 0.00015365,
    "CNIP": 0.00218634,
    "COFFEE": 0.00001674,
    "CRYSTAL": 0.00061399,
    "CTX": 0.2704169,
    "DO": 1.3e-9,
    "DOGE": 0.0009242,
    "ELPACO": 0.00277409,
    "FIRE": 4.8e-9,
    "FLX": 0.00000258,
    "FOOD": 3.1e-7,
    "FRG": 0.00070366,
    "FUN": 6.34950161,
    "FUTUREFLARE": 8.6e-7,
    "GRDX": 0.00190882,
    "HOTL": 0.00011822,
    "IDEV": 0.00070523,
    "JURASS": 0.00000107,
    "JURIS": 0.00000288,
    "KENNY": 7.9e-7,
    "KNEEL": 0.00049552,
    "KRQ": 1.6e-7,
    "LCM": 2e-7,
    "LCW": 0.00041213,
    "LEAPE": 2e-10,
    "LENNYL": 1.2e-9,
    "LENNYR": 1e-9,
    "LIX": 0.00001477,
    "LTK": 0.00688628,
    "LTRN": 1.1e-7,
    "MBA": 0.00000408,
    "MIOFF": 3e-8,
    "MIR": 0.00688737,
    "NHERA": 3e-8,
    "POG": 1.8e-7,
    "QUID": 0.00017098,
    "ROTTI": 1e-8,
    "SAYVE": 4.9e-7,
    "SELE": 0.01552234,
    "SKI": 0.00010693,
    "SMF": 0.00002498,
    "SMT": 0.00008752,
    "TCR": 0.00005968,
    "TEAI": 1.3e-7,
    "TEST": 0.00009112,
    "THC": 8.4e-7,
    "TNEWS": 0.00000175,
    "ULC": 0.000001,
    "USTRIX": 0.39736308,
    "UWU": 0.00003752,
    "VIMA": 0.00029729,
    "WAVAX": 16.85935074,
    "WETH": 1586.05858825,
    "MDOT": 1.2e-7,
    "CWLUNC": 0.00008596487729530263,
    "CWUSTC": 0.00626517152611408
  },
  "rows": [
    {
      "pairId": "amplunc-cwlunc",
      "type": "direct",
      "base": "AMPLUNC",
      "quote": "CWLUNC",
      "priceUsd": 0.000111,
      "marketCap": 14334.760246,
      "fdv": 14334.760246,
      "liquidity": 178.927912,
      "volume24h": 0,
      "volume7d": 0,
      "traders": 2,
      "volumeSource": "standard",
      "liquiditySource": "pool_tvl",
      "marketCapSource": "token_market_stats:cw20_token_info",
      "fdvSource": "token_market_stats:cw20_token_info",
      "tokenSupplySource": "cw20_token_info",
      "tokenPriceSource": "AMPLUNC"
    },
    {
      "pairId": "amplunc-cwustc",
      "type": "routed",
      "base": "AMPLUNC",
      "quote": "CWUSTC",
      "priceUsd": 0.000111,
      "marketCap": 14334.760246,
      "fdv": 14334.760246,
      "liquidity": 159.850208,
      "volume24h": 0,
      "volume7d": 0,
      "traders": 1,
      "volumeSource": "standard",
      "liquiditySource": "routed_estimate",
      "marketCapSource": "token_market_stats:cw20_token_info",
      "fdvSource": "token_market_stats:cw20_token_info",
      "tokenSupplySource": "cw20_token_info",
      "tokenPriceSource": "AMPLUNC"
    },
    {
      "pairId": "amplunc-lunc",
      "type": "routed",
      "base": "AMPLUNC",
      "quote": "LUNC",
      "priceUsd": 0.000111,
      "marketCap": 14334.760246,
      "fdv": 14334.760246,
      "liquidity": 178.927912,
      "volume24h": 0,
      "volume7d": 0,
      "traders": 3,
      "volumeSource": "standard",
      "liquiditySource": "routed_estimate",
      "marketCapSource": "token_market_stats:cw20_token_info",
      "fdvSource": "token_market_stats:cw20_token_info",
      "tokenSupplySource": "cw20_token_info",
      "tokenPriceSource": "AMPLUNC"
    },
    {
      "pairId": "amplunc-mdot",
      "type": "routed",
      "base": "AMPLUNC",
      "quote": "MDOT",
      "priceUsd": 0.000111,
      "marketCap": 14334.760246,
      "fdv": 14334.760246,
      "liquidity": 0.039613,
      "volume24h": 0,
      "volume7d": 0,
      "traders": 0,
      "volumeSource": "standard",
      "liquiditySource": "routed_estimate",
      "marketCapSource": "token_market_stats:cw20_token_info",
      "fdvSource": "token_market_stats:cw20_token_info",
      "tokenSupplySource": "cw20_token_info",
      "tokenPriceSource": "AMPLUNC"
    },
    {
      "pairId": "amplunc-ustc",
      "type": "routed",
      "base": "AMPLUNC",
      "quote": "USTC",
      "priceUsd": 0.000111,
      "marketCap": 14334.760246,
      "fdv": 14334.760246,
      "liquidity": 146.01063,
      "volume24h": 0,
      "volume7d": 0,
      "traders": 0,
      "volumeSource": "standard",
      "liquiditySource": "routed_estimate",
      "marketCapSource": "token_market_stats:cw20_token_info",
      "fdvSource": "token_market_stats:cw20_token_info",
      "tokenSupplySource": "cw20_token_info",
      "tokenPriceSource": "AMPLUNC"
    },
    {
      "pairId": "astro-amplunc",
      "type": "routed",
      "base": "ASTRO",
      "quote": "AMPLUNC",
      "priceUsd": 0.000545,
      "marketCap": 544679.999455,
      "fdv": 544679.999455,
      "liquidity": 0.059133,
      "volume24h": 0,
      "volume7d": 0,
      "traders": 1,
      "volumeSource": "standard",
      "liquiditySource": "routed_estimate",
      "marketCapSource": "token_market_stats:cw20_token_info",
      "fdvSource": "token_market_stats:cw20_token_info",
      "tokenSupplySource": "cw20_token_info",
      "tokenPriceSource": "ASTRO"
    },
    {
      "pairId": "astro-cwlunc",
      "type": "direct",
      "base": "ASTRO",
      "quote": "CWLUNC",
      "priceUsd": 0.000545,
      "marketCap": 544679.999455,
      "fdv": 544679.999455,
      "liquidity": 0.065959,
      "volume24h": 0,
      "volume7d": 25.185531877625,
      "traders": 9,
      "volumeSource": "standard",
      "liquiditySource": "pool_tvl",
      "marketCapSource": "token_market_stats:cw20_token_info",
      "fdvSource": "token_market_stats:cw20_token_info",
      "tokenSupplySource": "cw20_token_info",
      "tokenPriceSource": "ASTRO"
    },
    {
      "pairId": "astro-cwustc",
      "type": "routed",
      "base": "ASTRO",
      "quote": "CWUSTC",
      "priceUsd": 0.000545,
      "marketCap": 544679.999455,
      "fdv": 544679.999455,
      "liquidity": 0.057366,
      "volume24h": 0,
      "volume7d": 0,
      "traders": 2,
      "volumeSource": "standard",
      "liquiditySource": "routed_estimate",
      "marketCapSource": "token_market_stats:cw20_token_info",
      "fdvSource": "token_market_stats:cw20_token_info",
      "tokenSupplySource": "cw20_token_info",
      "tokenPriceSource": "ASTRO"
    },
    {
      "pairId": "astro-lunc",
      "type": "routed",
      "base": "ASTRO",
      "quote": "LUNC",
      "priceUsd": 0.000545,
      "marketCap": 544679.999455,
      "fdv": 544679.999455,
      "liquidity": 0.065959,
      "volume24h": 0,
      "volume7d": 41.524097175925,
      "traders": 8,
      "volumeSource": "standard",
      "liquiditySource": "routed_estimate",
      "marketCapSource": "token_market_stats:cw20_token_info",
      "fdvSource": "token_market_stats:cw20_token_info",
      "tokenSupplySource": "cw20_token_info",
      "tokenPriceSource": "ASTRO"
    },
    {
      "pairId": "astro-mdot",
      "type": "routed",
      "base": "ASTRO",
      "quote": "MDOT",
      "priceUsd": 0.000545,
      "marketCap": 544679.999455,
      "fdv": 544679.999455,
      "liquidity": 0.042057,
      "volume24h": 0,
      "volume7d": 0,
      "traders": 0,
      "volumeSource": "standard",
      "liquiditySource": "routed_estimate",
      "marketCapSource": "token_market_stats:cw20_token_info",
      "fdvSource": "token_market_stats:cw20_token_info",
      "tokenSupplySource": "cw20_token_info",
      "tokenPriceSource": "ASTRO"
    },
    {
      "pairId": "astro-ustc",
      "type": "routed",
      "base": "ASTRO",
      "quote": "USTC",
      "priceUsd": 0.000545,
      "marketCap": 544679.999455,
      "fdv": 544679.999455,
      "liquidity": 0.057145,
      "volume24h": 0,
      "volume7d": 0,
      "traders": 4,
      "volumeSource": "standard",
      "liquiditySource": "routed_estimate",
      "marketCapSource": "token_market_stats:cw20_token_info",
      "fdvSource": "token_market_stats:cw20_token_info",
      "tokenSupplySource": "cw20_token_info",
      "tokenPriceSource": "ASTRO"
    },
    {
      "pairId": "astro-wavax",
      "type": "routed",
      "base": "ASTRO",
      "quote": "WAVAX",
      "priceUsd": 0.000545,
      "marketCap": 544679.999455,
      "fdv": 544679.999455,
      "liquidity": 0.05656,
      "volume24h": 0,
      "volume7d": 0,
      "traders": 2,
      "volumeSource": "standard",
      "liquiditySource": "routed_estimate",
      "marketCapSource": "token_market_stats:cw20_token_info",
      "fdvSource": "token_market_stats:cw20_token_info",
      "tokenSupplySource": "cw20_token_info",
      "tokenPriceSource": "ASTRO"
    },
    {
      "pairId": "autc-lunc",
      "type": "direct",
      "base": "AUTC",
      "quote": "LUNC",
      "priceUsd": 0.00713,
      "marketCap": 4950294.538558,
      "fdv": 71301200,
      "liquidity": "",
      "volume24h": null,
      "volume7d": null,
      "traders": null,
      "volumeSource": "missing",
      "liquiditySource": "missing",
      "marketCapSource": "frontend_stats_supply_x_base_price",
      "fdvSource": "frontend_stats_totalSupply_x_base_price",
      "tokenSupplySource": "legacy_fallback",
      "tokenPriceSource": "audit_price_map"
    },
    {
      "pairId": "catc-lunc",
      "type": "direct",
      "base": "CATC",
      "quote": "LUNC",
      "priceUsd": 0.007229,
      "marketCap": 5018646.333103,
      "fdv": 72285700,
      "liquidity": "",
      "volume24h": null,
      "volume7d": null,
      "traders": null,
      "volumeSource": "missing",
      "liquiditySource": "missing",
      "marketCapSource": "frontend_stats_supply_x_base_price",
      "fdvSource": "frontend_stats_totalSupply_x_base_price",
      "tokenSupplySource": "legacy_fallback",
      "tokenPriceSource": "audit_price_map"
    },
    {
      "pairId": "chtc-lunc",
      "type": "direct",
      "base": "CHTC",
      "quote": "LUNC",
      "priceUsd": 1.030275,
      "marketCap": 715298718.082085,
      "fdv": 10302752000,
      "liquidity": "",
      "volume24h": null,
      "volume7d": null,
      "traders": null,
      "volumeSource": "missing",
      "liquiditySource": "missing",
      "marketCapSource": "frontend_stats_supply_x_base_price",
      "fdvSource": "frontend_stats_totalSupply_x_base_price",
      "tokenSupplySource": "legacy_fallback",
      "tokenPriceSource": "audit_price_map"
    },
    {
      "pairId": "cntc-lunc",
      "type": "direct",
      "base": "CNTC",
      "quote": "LUNC",
      "priceUsd": 0.001474,
      "marketCap": 1023693.961429,
      "fdv": 14744700,
      "liquidity": "",
      "volume24h": null,
      "volume7d": null,
      "traders": null,
      "volumeSource": "missing",
      "liquiditySource": "missing",
      "marketCapSource": "frontend_stats_supply_x_base_price",
      "fdvSource": "frontend_stats_totalSupply_x_base_price",
      "tokenSupplySource": "legacy_fallback",
      "tokenPriceSource": "audit_price_map"
    },
    {
      "pairId": "cwlunc-cwustc",
      "type": "direct",
      "base": "CWLUNC",
      "quote": "CWUSTC",
      "priceUsd": 0.000086,
      "marketCap": 85972156.476608,
      "fdv": 85972156.476608,
      "liquidity": 758.970126,
      "volume24h": 1214.773310527954,
      "volume7d": 1501.293349486684,
      "traders": 11,
      "volumeSource": "standard",
      "liquiditySource": "pool_tvl",
      "marketCapSource": "token_market_stats:cw20_token_info",
      "fdvSource": "token_market_stats:cw20_token_info",
      "tokenSupplySource": "cw20_token_info",
      "tokenPriceSource": "CWLUNC"
    },
    {
      "pairId": "cwlunc-lunc",
      "type": "direct",
      "base": "CWLUNC",
      "quote": "LUNC",
      "priceUsd": 0.000086,
      "marketCap": 85972156.476608,
      "fdv": 85972156.476608,
      "liquidity": 20610.276403,
      "volume24h": 5820.690339997488,
      "volume7d": 6165.3256194159,
      "traders": 46,
      "volumeSource": "legacy",
      "liquiditySource": "native_reserve",
      "marketCapSource": "token_market_stats:cw20_token_info",
      "fdvSource": "token_market_stats:cw20_token_info",
      "tokenSupplySource": "cw20_token_info",
      "tokenPriceSource": "CWLUNC"
    },
    {
      "pairId": "cwustc-lunc",
      "type": "routed",
      "base": "CWUSTC",
      "quote": "LUNC",
      "priceUsd": 0.006265,
      "marketCap": 6265171.526114,
      "fdv": 6265171.526114,
      "liquidity": 758.970126,
      "volume24h": 0,
      "volume7d": 0,
      "traders": 5,
      "volumeSource": "standard",
      "liquiditySource": "routed_estimate",
      "marketCapSource": "token_market_stats:cw20_token_info",
      "fdvSource": "token_market_stats:cw20_token_info",
      "tokenSupplySource": "cw20_token_info",
      "tokenPriceSource": "CWUSTC"
    },
    {
      "pairId": "cwustc-ustc",
      "type": "direct",
      "base": "CWUSTC",
      "quote": "USTC",
      "priceUsd": 0.006265,
      "marketCap": 6265171.526114,
      "fdv": 6265171.526114,
      "liquidity": 11017.094603,
      "volume24h": 1011.269847405839,
      "volume7d": 1150.389235740741,
      "traders": 27,
      "volumeSource": "standard",
      "liquiditySource": "native_reserve",
      "marketCapSource": "token_market_stats:cw20_token_info",
      "fdvSource": "token_market_stats:cw20_token_info",
      "tokenSupplySource": "cw20_token_info",
      "tokenPriceSource": "CWUSTC"
    },
    {
      "pairId": "dktc-lunc",
      "type": "direct",
      "base": "DKTC",
      "quote": "LUNC",
      "priceUsd": 0.001557,
      "marketCap": 1081194.170919,
      "fdv": 15572900,
      "liquidity": "",
      "volume24h": null,
      "volume7d": null,
      "traders": null,
      "volumeSource": "missing",
      "liquiditySource": "missing",
      "marketCapSource": "frontend_stats_supply_x_base_price",
      "fdvSource": "frontend_stats_totalSupply_x_base_price",
      "tokenSupplySource": "legacy_fallback",
      "tokenPriceSource": "audit_price_map"
    },
    {
      "pairId": "eutc-lunc",
      "type": "direct",
      "base": "EUTC",
      "quote": "LUNC",
      "priceUsd": 0.746837,
      "marketCap": 518513769.674045,
      "fdv": 7468374600,
      "liquidity": "",
      "volume24h": null,
      "volume7d": null,
      "traders": null,
      "volumeSource": "missing",
      "liquiditySource": "missing",
      "marketCapSource": "frontend_stats_supply_x_base_price",
      "fdvSource": "frontend_stats_totalSupply_x_base_price",
      "tokenSupplySource": "legacy_fallback",
      "tokenPriceSource": "audit_price_map"
    },
    {
      "pairId": "gbtc-lunc",
      "type": "direct",
      "base": "GBTC",
      "quote": "LUNC",
      "priceUsd": 0.013435,
      "marketCap": 9327572.620947,
      "fdv": 134349000,
      "liquidity": "",
      "volume24h": null,
      "volume7d": null,
      "traders": null,
      "volumeSource": "missing",
      "liquiditySource": "missing",
      "marketCapSource": "frontend_stats_supply_x_base_price",
      "fdvSource": "frontend_stats_totalSupply_x_base_price",
      "tokenSupplySource": "legacy_fallback",
      "tokenPriceSource": "audit_price_map"
    },
    {
      "pairId": "hktc-lunc",
      "type": "direct",
      "base": "HKTC",
      "quote": "LUNC",
      "priceUsd": 0.001276,
      "marketCap": 886150.294418,
      "fdv": 12763600,
      "liquidity": "",
      "volume24h": null,
      "volume7d": null,
      "traders": null,
      "volumeSource": "missing",
      "liquiditySource": "missing",
      "marketCapSource": "frontend_stats_supply_x_base_price",
      "fdvSource": "frontend_stats_totalSupply_x_base_price",
      "tokenSupplySource": "legacy_fallback",
      "tokenPriceSource": "audit_price_map"
    },
    {
      "pairId": "idtc-lunc",
      "type": "direct",
      "base": "IDTC",
      "quote": "LUNC",
      "priceUsd": 0.000001,
      "marketCap": 388.796394,
      "fdv": 5600,
      "liquidity": "",
      "volume24h": null,
      "volume7d": null,
      "traders": null,
      "volumeSource": "missing",
      "liquiditySource": "missing",
      "marketCapSource": "frontend_stats_supply_x_base_price",
      "fdvSource": "frontend_stats_totalSupply_x_base_price",
      "tokenSupplySource": "legacy_fallback",
      "tokenPriceSource": "audit_price_map"
    },
    {
      "pairId": "intc-lunc",
      "type": "direct",
      "base": "INTC",
      "quote": "LUNC",
      "priceUsd": 0.000105,
      "marketCap": 72552.184154,
      "fdv": 1045000,
      "liquidity": "",
      "volume24h": null,
      "volume7d": null,
      "traders": null,
      "volumeSource": "missing",
      "liquiditySource": "missing",
      "marketCapSource": "frontend_stats_supply_x_base_price",
      "fdvSource": "frontend_stats_totalSupply_x_base_price",
      "tokenSupplySource": "legacy_fallback",
      "tokenPriceSource": "audit_price_map"
    },
    {
      "pairId": "jptc-lunc",
      "type": "direct",
      "base": "JPTC",
      "quote": "LUNC",
      "priceUsd": 0.000063,
      "marketCap": 43552.138871,
      "fdv": 627300,
      "liquidity": "",
      "volume24h": null,
      "volume7d": null,
      "traders": null,
      "volumeSource": "missing",
      "liquiditySource": "missing",
      "marketCapSource": "frontend_stats_supply_x_base_price",
      "fdvSource": "frontend_stats_totalSupply_x_base_price",
      "tokenSupplySource": "legacy_fallback",
      "tokenPriceSource": "audit_price_map"
    },
    {
      "pairId": "krtc-lunc",
      "type": "direct",
      "base": "KRTC",
      "quote": "LUNC",
      "priceUsd": 0.000047,
      "marketCap": 32742.210571,
      "fdv": 471600,
      "liquidity": "",
      "volume24h": null,
      "volume7d": null,
      "traders": null,
      "volumeSource": "missing",
      "liquiditySource": "missing",
      "marketCapSource": "frontend_stats_supply_x_base_price",
      "fdvSource": "frontend_stats_totalSupply_x_base_price",
      "tokenSupplySource": "legacy_fallback",
      "tokenPriceSource": "audit_price_map"
    },
    {
      "pairId": "mdot-cwlunc",
      "type": "direct",
      "base": "MDOT",
      "quote": "CWLUNC",
      "priceUsd": 0,
      "marketCap": 2.479423,
      "fdv": 2.479423,
      "liquidity": 0.048544,
      "volume24h": 0,
      "volume7d": 0,
      "traders": 2,
      "volumeSource": "standard",
      "liquiditySource": "pool_tvl",
      "marketCapSource": "token_market_stats:cw20_token_info",
      "fdvSource": "token_market_stats:cw20_token_info",
      "tokenSupplySource": "cw20_token_info",
      "tokenPriceSource": "MDOT"
    },
    {
      "pairId": "mdot-cwustc",
      "type": "routed",
      "base": "MDOT",
      "quote": "CWUSTC",
      "priceUsd": 0,
      "marketCap": 2.479423,
      "fdv": 2.479423,
      "liquidity": 0.042287,
      "volume24h": 0,
      "volume7d": 0,
      "traders": 1,
      "volumeSource": "standard",
      "liquiditySource": "routed_estimate",
      "marketCapSource": "token_market_stats:cw20_token_info",
      "fdvSource": "token_market_stats:cw20_token_info",
      "tokenSupplySource": "cw20_token_info",
      "tokenPriceSource": "MDOT"
    },
    {
      "pairId": "mdot-lunc",
      "type": "routed",
      "base": "MDOT",
      "quote": "LUNC",
      "priceUsd": 0,
      "marketCap": 2.479423,
      "fdv": 2.479423,
      "liquidity": 0.048544,
      "volume24h": 0,
      "volume7d": 0,
      "traders": 0,
      "volumeSource": "standard",
      "liquiditySource": "routed_estimate",
      "marketCapSource": "token_market_stats:cw20_token_info",
      "fdvSource": "token_market_stats:cw20_token_info",
      "tokenSupplySource": "cw20_token_info",
      "tokenPriceSource": "MDOT"
    },
    {
      "pairId": "mdot-rebase",
      "type": "routed",
      "base": "MDOT",
      "quote": "REBASE",
      "priceUsd": 0,
      "marketCap": 2.479423,
      "fdv": 2.479423,
      "liquidity": 0.040648,
      "volume24h": 0,
      "volume7d": 0,
      "traders": 0,
      "volumeSource": "standard",
      "liquiditySource": "routed_estimate",
      "marketCapSource": "token_market_stats:cw20_token_info",
      "fdvSource": "token_market_stats:cw20_token_info",
      "tokenSupplySource": "cw20_token_info",
      "tokenPriceSource": "MDOT"
    },
    {
      "pairId": "mdot-ustc",
      "type": "routed",
      "base": "MDOT",
      "quote": "USTC",
      "priceUsd": 0,
      "marketCap": 2.479423,
      "fdv": 2.479423,
      "liquidity": 0.039241,
      "volume24h": 0,
      "volume7d": 0.490322416286,
      "traders": 2,
      "volumeSource": "standard",
      "liquiditySource": "routed_estimate",
      "marketCapSource": "token_market_stats:cw20_token_info",
      "fdvSource": "token_market_stats:cw20_token_info",
      "tokenSupplySource": "cw20_token_info",
      "tokenPriceSource": "MDOT"
    },
    {
      "pairId": "mdot-wavax",
      "type": "routed",
      "base": "MDOT",
      "quote": "WAVAX",
      "priceUsd": 0,
      "marketCap": 2.479423,
      "fdv": 2.479423,
      "liquidity": 0.041717,
      "volume24h": 0,
      "volume7d": 0,
      "traders": 0,
      "volumeSource": "standard",
      "liquiditySource": "routed_estimate",
      "marketCapSource": "token_market_stats:cw20_token_info",
      "fdvSource": "token_market_stats:cw20_token_info",
      "tokenSupplySource": "cw20_token_info",
      "tokenPriceSource": "MDOT"
    },
    {
      "pairId": "mdot-weso",
      "type": "routed",
      "base": "MDOT",
      "quote": "WESO",
      "priceUsd": 0,
      "marketCap": 2.479423,
      "fdv": 2.479423,
      "liquidity": 0.039241,
      "volume24h": 0,
      "volume7d": 0,
      "traders": 0,
      "volumeSource": "standard",
      "liquiditySource": "routed_estimate",
      "marketCapSource": "token_market_stats:cw20_token_info",
      "fdvSource": "token_market_stats:cw20_token_info",
      "tokenSupplySource": "cw20_token_info",
      "tokenPriceSource": "MDOT"
    },
    {
      "pairId": "mytc-lunc",
      "type": "direct",
      "base": "MYTC",
      "quote": "LUNC",
      "priceUsd": 0.002522,
      "marketCap": 1751020.929081,
      "fdv": 25220700,
      "liquidity": "",
      "volume24h": null,
      "volume7d": null,
      "traders": null,
      "volumeSource": "missing",
      "liquiditySource": "missing",
      "marketCapSource": "frontend_stats_supply_x_base_price",
      "fdvSource": "frontend_stats_totalSupply_x_base_price",
      "tokenSupplySource": "legacy_fallback",
      "tokenPriceSource": "audit_price_map"
    },
    {
      "pairId": "phtc-lunc",
      "type": "direct",
      "base": "PHTC",
      "quote": "LUNC",
      "priceUsd": 0.000163,
      "marketCap": 112973.123498,
      "fdv": 1627200,
      "liquidity": "",
      "volume24h": null,
      "volume7d": null,
      "traders": null,
      "volumeSource": "missing",
      "liquiditySource": "missing",
      "marketCapSource": "frontend_stats_supply_x_base_price",
      "fdvSource": "frontend_stats_totalSupply_x_base_price",
      "tokenSupplySource": "legacy_fallback",
      "tokenPriceSource": "audit_price_map"
    },
    {
      "pairId": "rebase-amplunc",
      "type": "routed",
      "base": "REBASE",
      "quote": "AMPLUNC",
      "priceUsd": 0.003374,
      "marketCap": 132785.928777,
      "fdv": 674835.408455,
      "liquidity": 143.674765,
      "volume24h": 0,
      "volume7d": 0,
      "traders": 0,
      "volumeSource": "standard",
      "liquiditySource": "routed_estimate",
      "marketCapSource": "token_market_stats:rebase_curve_plus_override",
      "fdvSource": "token_market_stats:rebase_curve_plus_override",
      "tokenSupplySource": "rebase_curve_plus_override",
      "tokenPriceSource": "REBASE"
    },
    {
      "pairId": "rebase-astro",
      "type": "routed",
      "base": "REBASE",
      "quote": "ASTRO",
      "priceUsd": 0.003374,
      "marketCap": 132785.928777,
      "fdv": 674835.408455,
      "liquidity": 0.057999,
      "volume24h": 0,
      "volume7d": 0,
      "traders": 0,
      "volumeSource": "standard",
      "liquiditySource": "routed_estimate",
      "marketCapSource": "token_market_stats:rebase_curve_plus_override",
      "fdvSource": "token_market_stats:rebase_curve_plus_override",
      "tokenSupplySource": "rebase_curve_plus_override",
      "tokenPriceSource": "REBASE"
    },
    {
      "pairId": "rebase-cwlunc",
      "type": "routed",
      "base": "REBASE",
      "quote": "CWLUNC",
      "priceUsd": 0.003374,
      "marketCap": 132785.928777,
      "fdv": 674835.408455,
      "liquidity": 650.770591,
      "volume24h": 0,
      "volume7d": 0,
      "traders": 2,
      "volumeSource": "standard",
      "liquiditySource": "routed_estimate",
      "marketCapSource": "token_market_stats:rebase_curve_plus_override",
      "fdvSource": "token_market_stats:rebase_curve_plus_override",
      "tokenSupplySource": "rebase_curve_plus_override",
      "tokenPriceSource": "REBASE"
    },
    {
      "pairId": "rebase-cwustc",
      "type": "direct",
      "base": "REBASE",
      "quote": "CWUSTC",
      "priceUsd": 0.003374,
      "marketCap": 132785.928777,
      "fdv": 674835.408455,
      "liquidity": 3749.038463,
      "volume24h": 0,
      "volume7d": 0,
      "traders": 159,
      "volumeSource": "legacy",
      "liquiditySource": "placeholder_ratio_from:rebase-ustc",
      "marketCapSource": "token_market_stats:rebase_curve_plus_override",
      "fdvSource": "token_market_stats:rebase_curve_plus_override",
      "tokenSupplySource": "rebase_curve_plus_override",
      "tokenPriceSource": "REBASE"
    },
    {
      "pairId": "rebase-lunc",
      "type": "routed",
      "base": "REBASE",
      "quote": "LUNC",
      "priceUsd": 0.003374,
      "marketCap": 132785.928777,
      "fdv": 674835.408455,
      "liquidity": 647.905573,
      "volume24h": 0,
      "volume7d": 0,
      "traders": 4,
      "volumeSource": "standard",
      "liquiditySource": "routed_estimate",
      "marketCapSource": "token_market_stats:rebase_curve_plus_override",
      "fdvSource": "token_market_stats:rebase_curve_plus_override",
      "tokenSupplySource": "rebase_curve_plus_override",
      "tokenPriceSource": "REBASE"
    },
    {
      "pairId": "rebase-ustc",
      "type": "direct",
      "base": "REBASE",
      "quote": "USTC",
      "priceUsd": 0.003374,
      "marketCap": 132785.928777,
      "fdv": 674835.408455,
      "liquidity": 22053.167429,
      "volume24h": 150.963052882796,
      "volume7d": 997.492177374648,
      "traders": 159,
      "volumeSource": "legacy",
      "liquiditySource": "native_reserve",
      "marketCapSource": "token_market_stats:rebase_curve_plus_override",
      "fdvSource": "token_market_stats:rebase_curve_plus_override",
      "tokenSupplySource": "rebase_curve_plus_override",
      "tokenPriceSource": "REBASE"
    },
    {
      "pairId": "rebase-wavax",
      "type": "routed",
      "base": "REBASE",
      "quote": "WAVAX",
      "priceUsd": 0.003374,
      "marketCap": 132785.928777,
      "fdv": 674835.408455,
      "liquidity": 9.451917,
      "volume24h": 0,
      "volume7d": 0,
      "traders": 0,
      "volumeSource": "standard",
      "liquiditySource": "routed_estimate",
      "marketCapSource": "token_market_stats:rebase_curve_plus_override",
      "fdvSource": "token_market_stats:rebase_curve_plus_override",
      "tokenSupplySource": "rebase_curve_plus_override",
      "tokenPriceSource": "REBASE"
    },
    {
      "pairId": "sdtc-lunc",
      "type": "direct",
      "base": "SDTC",
      "quote": "LUNC",
      "priceUsd": 4.522116,
      "marketCap": 3139611754.524283,
      "fdv": 45221164900,
      "liquidity": "",
      "volume24h": null,
      "volume7d": null,
      "traders": null,
      "volumeSource": "missing",
      "liquiditySource": "missing",
      "marketCapSource": "frontend_stats_supply_x_base_price",
      "fdvSource": "frontend_stats_totalSupply_x_base_price",
      "tokenSupplySource": "legacy_fallback",
      "tokenPriceSource": "audit_price_map"
    },
    {
      "pairId": "setc-lunc",
      "type": "direct",
      "base": "SETC",
      "quote": "LUNC",
      "priceUsd": 0.001079,
      "marketCap": 748814.911188,
      "fdv": 10785500,
      "liquidity": "",
      "volume24h": null,
      "volume7d": null,
      "traders": null,
      "volumeSource": "missing",
      "liquiditySource": "missing",
      "marketCapSource": "frontend_stats_supply_x_base_price",
      "fdvSource": "frontend_stats_totalSupply_x_base_price",
      "tokenSupplySource": "legacy_fallback",
      "tokenPriceSource": "audit_price_map"
    },
    {
      "pairId": "sgtc-lunc",
      "type": "direct",
      "base": "SGTC",
      "quote": "LUNC",
      "priceUsd": 0.007827,
      "marketCap": 5433818.396281,
      "fdv": 78265600,
      "liquidity": "",
      "volume24h": null,
      "volume7d": null,
      "traders": null,
      "volumeSource": "missing",
      "liquiditySource": "missing",
      "marketCapSource": "frontend_stats_supply_x_base_price",
      "fdvSource": "frontend_stats_totalSupply_x_base_price",
      "tokenSupplySource": "legacy_fallback",
      "tokenPriceSource": "audit_price_map"
    },
    {
      "pairId": "thtc-lunc",
      "type": "direct",
      "base": "THTC",
      "quote": "LUNC",
      "priceUsd": 0.000307,
      "marketCap": 212838.254299,
      "fdv": 3065600,
      "liquidity": "",
      "volume24h": null,
      "volume7d": null,
      "traders": null,
      "volumeSource": "missing",
      "liquiditySource": "missing",
      "marketCapSource": "frontend_stats_supply_x_base_price",
      "fdvSource": "frontend_stats_totalSupply_x_base_price",
      "tokenSupplySource": "legacy_fallback",
      "tokenPriceSource": "audit_price_map"
    },
    {
      "pairId": "ustc-cwlunc",
      "type": "routed",
      "base": "USTC",
      "quote": "CWLUNC",
      "priceUsd": 0.000086,
      "marketCap": 85972156.476608,
      "fdv": 85972156.476608,
      "liquidity": 758.970126,
      "volume24h": 0,
      "volume7d": 0,
      "traders": 3,
      "volumeSource": "standard",
      "liquiditySource": "routed_estimate",
      "marketCapSource": "token_market_stats:cw20_token_info",
      "fdvSource": "token_market_stats:cw20_token_info",
      "tokenSupplySource": "cw20_token_info",
      "tokenPriceSource": "CWLUNC"
    },
    {
      "pairId": "ustc-lunc",
      "type": "direct",
      "base": "USTC",
      "quote": "LUNC",
      "priceUsd": 0.006265,
      "marketCap": 555233859.352961,
      "fdv": 555233859.352961,
      "liquidity": 758.970126,
      "volume24h": 1015.044434746715,
      "volume7d": 1281.006386390052,
      "traders": 30,
      "volumeSource": "standard",
      "liquiditySource": "routed_estimate",
      "marketCapSource": "token_market_stats:native_bank_supply",
      "fdvSource": "token_market_stats:native_bank_supply",
      "tokenSupplySource": "native_bank_supply",
      "tokenPriceSource": "USTC"
    },
    {
      "pairId": "wavax-amplunc",
      "type": "routed",
      "base": "WAVAX",
      "quote": "AMPLUNC",
      "priceUsd": 16.859351,
      "marketCap": 7710.001991,
      "fdv": 7710.001991,
      "liquidity": 9.999033,
      "volume24h": 0,
      "volume7d": 0,
      "traders": 1,
      "volumeSource": "standard",
      "liquiditySource": "routed_estimate",
      "marketCapSource": "token_market_stats:cw20_token_info",
      "fdvSource": "token_market_stats:cw20_token_info",
      "tokenSupplySource": "cw20_token_info",
      "tokenPriceSource": "WAVAX"
    },
    {
      "pairId": "wavax-cwlunc",
      "type": "direct",
      "base": "WAVAX",
      "quote": "CWLUNC",
      "priceUsd": 16.859351,
      "marketCap": 7710.001991,
      "fdv": 7710.001991,
      "liquidity": 11.1475,
      "volume24h": 0,
      "volume7d": 0,
      "traders": 6,
      "volumeSource": "standard",
      "liquiditySource": "pool_tvl",
      "marketCapSource": "token_market_stats:cw20_token_info",
      "fdvSource": "token_market_stats:cw20_token_info",
      "tokenSupplySource": "cw20_token_info",
      "tokenPriceSource": "WAVAX"
    },
    {
      "pairId": "wavax-cwustc",
      "type": "routed",
      "base": "WAVAX",
      "quote": "CWUSTC",
      "priceUsd": 16.859351,
      "marketCap": 7710.001991,
      "fdv": 7710.001991,
      "liquidity": 8.968633,
      "volume24h": 0,
      "volume7d": 0,
      "traders": 0,
      "volumeSource": "standard",
      "liquiditySource": "routed_estimate",
      "marketCapSource": "token_market_stats:cw20_token_info",
      "fdvSource": "token_market_stats:cw20_token_info",
      "tokenSupplySource": "cw20_token_info",
      "tokenPriceSource": "WAVAX"
    },
    {
      "pairId": "wavax-lunc",
      "type": "routed",
      "base": "WAVAX",
      "quote": "LUNC",
      "priceUsd": 16.859351,
      "marketCap": 7710.001991,
      "fdv": 7710.001991,
      "liquidity": 11.1475,
      "volume24h": 0,
      "volume7d": 0,
      "traders": 2,
      "volumeSource": "standard",
      "liquiditySource": "routed_estimate",
      "marketCapSource": "token_market_stats:cw20_token_info",
      "fdvSource": "token_market_stats:cw20_token_info",
      "tokenSupplySource": "cw20_token_info",
      "tokenPriceSource": "WAVAX"
    },
    {
      "pairId": "wavax-ustc",
      "type": "routed",
      "base": "WAVAX",
      "quote": "USTC",
      "priceUsd": 16.859351,
      "marketCap": 7710.001991,
      "fdv": 7710.001991,
      "liquidity": 9.398792,
      "volume24h": 0,
      "volume7d": 0,
      "traders": 1,
      "volumeSource": "standard",
      "liquiditySource": "routed_estimate",
      "marketCapSource": "token_market_stats:cw20_token_info",
      "fdvSource": "token_market_stats:cw20_token_info",
      "tokenSupplySource": "cw20_token_info",
      "tokenPriceSource": "WAVAX"
    },
    {
      "pairId": "weso-amplunc",
      "type": "routed",
      "base": "WESO",
      "quote": "AMPLUNC",
      "priceUsd": 0.003425,
      "marketCap": 2378129.733949,
      "fdv": 34253215.130036,
      "liquidity": 146.010822,
      "volume24h": 0,
      "volume7d": 0,
      "traders": 1,
      "volumeSource": "standard",
      "liquiditySource": "routed_estimate",
      "marketCapSource": "token_market_stats:weso_curve",
      "fdvSource": "token_market_stats:weso_curve",
      "tokenSupplySource": "weso_curve",
      "tokenPriceSource": "WESO"
    },
    {
      "pairId": "weso-astro",
      "type": "routed",
      "base": "WESO",
      "quote": "ASTRO",
      "priceUsd": 0.003425,
      "marketCap": 2378129.733949,
      "fdv": 34253215.130036,
      "liquidity": 0.057145,
      "volume24h": 0,
      "volume7d": 0,
      "traders": 1,
      "volumeSource": "standard",
      "liquiditySource": "routed_estimate",
      "marketCapSource": "token_market_stats:weso_curve",
      "fdvSource": "token_market_stats:weso_curve",
      "tokenSupplySource": "weso_curve",
      "tokenPriceSource": "WESO"
    },
    {
      "pairId": "weso-cwlunc",
      "type": "direct",
      "base": "WESO",
      "quote": "CWLUNC",
      "priceUsd": 0.003425,
      "marketCap": 2378129.733949,
      "fdv": 34253215.130036,
      "liquidity": 6721.904297,
      "volume24h": 0,
      "volume7d": 0,
      "traders": 198,
      "volumeSource": "legacy",
      "liquiditySource": "placeholder_ratio_from:weso-lunc",
      "marketCapSource": "token_market_stats:weso_curve",
      "fdvSource": "token_market_stats:weso_curve",
      "tokenSupplySource": "weso_curve",
      "tokenPriceSource": "WESO"
    },
    {
      "pairId": "weso-cwustc",
      "type": "routed",
      "base": "WESO",
      "quote": "CWUSTC",
      "priceUsd": 0.003425,
      "marketCap": 2378129.733949,
      "fdv": 34253215.130036,
      "liquidity": 661.149767,
      "volume24h": 0,
      "volume7d": 0,
      "traders": 1,
      "volumeSource": "standard",
      "liquiditySource": "routed_estimate",
      "marketCapSource": "token_market_stats:weso_curve",
      "fdvSource": "token_market_stats:weso_curve",
      "tokenSupplySource": "weso_curve",
      "tokenPriceSource": "WESO"
    },
    {
      "pairId": "weso-lunc",
      "type": "direct",
      "base": "WESO",
      "quote": "LUNC",
      "priceUsd": 0.003425,
      "marketCap": 2378129.733949,
      "fdv": 34253215.130036,
      "liquidity": 96027.204239,
      "volume24h": 409.794416735112,
      "volume7d": 2225.11841904975,
      "traders": 198,
      "volumeSource": "legacy",
      "liquiditySource": "native_reserve",
      "marketCapSource": "token_market_stats:weso_curve",
      "fdvSource": "token_market_stats:weso_curve",
      "tokenSupplySource": "weso_curve",
      "tokenPriceSource": "WESO"
    },
    {
      "pairId": "weso-rebase",
      "type": "routed",
      "base": "WESO",
      "quote": "REBASE",
      "priceUsd": 0.003425,
      "marketCap": 2378129.733949,
      "fdv": 34253215.130036,
      "liquidity": 664.65948,
      "volume24h": 0,
      "volume7d": 0,
      "traders": 5,
      "volumeSource": "standard",
      "liquiditySource": "routed_estimate",
      "marketCapSource": "token_market_stats:weso_curve",
      "fdvSource": "token_market_stats:weso_curve",
      "tokenSupplySource": "weso_curve",
      "tokenPriceSource": "WESO"
    },
    {
      "pairId": "weso-ustc",
      "type": "routed",
      "base": "WESO",
      "quote": "USTC",
      "priceUsd": 0.003425,
      "marketCap": 2378129.733949,
      "fdv": 34253215.130036,
      "liquidity": 662.094511,
      "volume24h": 0,
      "volume7d": 0,
      "traders": 2,
      "volumeSource": "standard",
      "liquiditySource": "routed_estimate",
      "marketCapSource": "token_market_stats:weso_curve",
      "fdvSource": "token_market_stats:weso_curve",
      "tokenSupplySource": "weso_curve",
      "tokenPriceSource": "WESO"
    },
    {
      "pairId": "weso-wavax",
      "type": "routed",
      "base": "WESO",
      "quote": "WAVAX",
      "priceUsd": 0.003425,
      "marketCap": 2378129.733949,
      "fdv": 34253215.130036,
      "liquidity": 9.576565,
      "volume24h": 0,
      "volume7d": 0,
      "traders": 2,
      "volumeSource": "standard",
      "liquiditySource": "routed_estimate",
      "marketCapSource": "token_market_stats:weso_curve",
      "fdvSource": "token_market_stats:weso_curve",
      "tokenSupplySource": "weso_curve",
      "tokenPriceSource": "WESO"
    }
  ]
}
